{"r2qkbnr/pp2pppp/2n5/1B6/2pP2b1/5N2/PP3PPP/RNBQK2R w KQkq - 0 7":{"moves":{"h1g1":{"score":140,"line":["e7e6","b5c6"]},"h1f1":{"score":179,"line":["e7e6","b5c6"]},"e1e2":{"score":171,"line":["e7e6","c1e3"]},"e1f1":{"score":140,"line":["e7e6","b1c3"]},"e1d2":{"score":294,"line":["d8a5"]},"e1g1":{"score":-29,"line":["e7e6","b1c3"]},"d1d2":{"score":210,"line":["g4f3"]},"d1d3":{"score":1266,"line":["c4d3"]},"d1c2":{"score":179,"line":["g4f3","g2f3"]},"d1b3":{"score":1269,"line":["c4b3"]},"d1a4":{"score":71,"line":["g4f3"]},"d1e2":{"score":62,"line":["a8c8","e1g1"]},"c1d2":{"score":82,"line":["e7e6","e1g1"]},"c1e3":{"score":49,"line":["e7e6"]},"c1f4":{"score":34,"line":["e7e6"]},"c1g5":{"score":38,"line":["h7h6"]},"c1h6":{"score":551,"line":["g8h6","h2h3"]},"b1d2":{"score":29,"line":["e7e6"]},"b1a3":{"score":73,"line":["e7e6","b5c6"]},"b1c3":{"score":3,"line":["e7e6"]},"h2h3":{"score":-8,"line":["g4h5"]},"h2h4":{"score":134,"line":["e7e6","b5c6"]},"g2g3":{"score":276,"line":["d8d5"]},"b2b3":{"score":450,"line":["d8a5"]},"b2b4":{"score":145,"line":["e7e6"]},"a2a3":{"score":69,"line":["g8f6"]},"a2a4":{"score":73,"line":["e7e6","e1g1"]},"f3h4":{"score":1284,"line":["g4d1","b1c3"]},"f3d2":{"score":1029,"line":["g4d1"]},"f3e5":{"score":778,"line":["g4d1","e5c6"]},"f3g5":{"score":1010,"line":["g4d1","b5c6"]},"f3g1":{"score":1033,"line":["g4d1","b5c6"]},"d4d5":{"score":-29,"line":["a7a6","b5a4"]},"d4d6":{"score":116,"line":["d8d6"]},"b5c4":{"score":37,"line":["e7e6"]},"b5a4":{"score":100,"line":["e7e6"]},"b5a6":{"score":703,"line":["d8a5","b1c3"]},"b5c6":{"score":67,"line":["b7c6"]}},"bestMove":"f3h4"},"rnbqkbnr/pp3pp1/2p1p2p/3p4/3PP3/2N5/PPP1NPPP/R1BQKB1R w KQkq - 0 5":{"moves":{"h1g1":{"score":43,"line":["b7b5"]},"e1d2":{"score":167,"line":["g8f6","e4e5"]},"d1d2":{"score":19,"line":["g8f6","d2d3"]},"d1d3":{"score":-3,"line":["g8e7","e2g3"]},"c1d2":{"score":7,"line":["b8d7","d2e3"]},"c1e3":{"score":-35,"line":["b8d7"]},"c1f4":{"score":-26,"line":["g8e7","e2g3"]},"c1g5":{"score":543,"line":["h6g5"]},"c1h6":{"score":452,"line":["h8h6"]},"a1b1":{"score":-12,"line":["d5e4"]},"h2h3":{"score":0,"line":["g8f6","e4e5","f6d7","e2f4","c6c5","f4e6"]},"h2h4":{"score":8,"line":["g8f6","d1d3"]},"g2g3":{"score":-33,"line":["b8d7"]},"g2g4":{"score":13,"line":["g8f6","e4e5"]},"f2f3":{"score":54,"line":["d8b6","e2g3"]},"f2f4":{"score":12,"line":["b8d7","g2g3"]},"e2g3":{"score":-35,"line":["g8f6","c1e3"]},"e2g1":{"score":57,"line":["g8f6","e4e5"]},"e2f4":{"score":-23,"line":["f8b4"]},"b2b3":{"score":22,"line":["g8f6"]},"b2b4":{"score":167,"line":["f8b4","c1d2"]},"a2a3":{"score":1,"line":["b8d7","e2g3"]},"a2a4":{"score":26,"line":["f8b4"]},"c3a4":{"score":89,"line":["d5e4","a4c3"]},"c3b5":{"score":400,"line":["c6b5","e4e5"]},"c3d5":{"score":345,"line":["e6d5"]},"c3b1":{"score":62,"line":["d5e4","b1c3"]},"e4e5":{"score":35,"line":["g8e7","e2g3"]},"e4d5":{"score":59,"line":["c6d5"]}},"bestMove":"c1g5"},"rn1qkbnr/pb3ppp/2p1p3/1p1p4/3PP3/P1NQ4/1PP2PPP/R1B1KBNR w KQkq - 1 6":{"moves":{"g1e2":{"score":-10,"line":["b8d7","e4d5"]},"g1f3":{"score":-15,"line":["b8d7","f1e2"]},"g1h3":{"score":-22,"line":["d5e4","c3e4"]},"f1e2":{"score":-22,"line":["a7a6","g1f3"]},"e1e2":{"score":195,"line":["d8a5","a1a2"]},"e1d1":{"score":158,"line":["d5e4"]},"e1d2":{"score":167,"line":["d5e4","c3e4"]},"c1d2":{"score":36,"line":["a7a6","f1e2"]},"c1e3":{"score":23,"line":["a7a5","e4e5"]},"c1f4":{"score":-15,"line":["g8f6","f1e2"]},"c1g5":{"score":482,"line":["d8g5","g1f3"]},"c1h6":{"score":531,"line":["g8h6","e4d5"]},"a1a2":{"score":66,"line":["d5e4","c3e4"]},"a1b1":{"score":30,"line":["d5e4"]},"h2h3":{"score":57,"line":["a7a6"]},"h2h4":{"score":33,"line":["a7a6"]},"g2g3":{"score":12,"line":["a7a5","e4e5"]},"g2g4":{"score":46,"line":["g8f6"]},"f2f3":{"score":62,"line":["a7a6","g1h3"]},"f2f4":{"score":14,"line":["d5e4","c3e4"]},"b2b3":{"score":17,"line":["g8f6","e4d5","e6d5","g1f3","b8d7","d3e3"]},"b2b4":{"score":88,"line":["a7a5","b4a5"]},"d3d2":{"score":12,"line":["d5e4","c3e4"]},"d3d1":{"score":35,"line":["a7a6","g1f3"]},"d3e3":{"score":-27,"line":["d5e4"]},"d3f3":{"score":73,"line":["a7a6"]},"d3g3":{"score":-12,"line":["d5e4"]},"d3h3":{"score":16,"line":["d5e4","h3e3"]},"d3e2":{"score":50,"line":["a7a6"]},"d3c4":{"score":1277,"line":["b5c4"]},"d3b5":{"score":1036,"line":["c6b5"]},"c3a4":{"score":514,"line":["b5a4","e4e5"]},"c3a2":{"score":87,"line":["d5e4","d3e4"]},"c3e2":{"score":87,"line":["d5e4","d3e4"]},"c3b5":{"score":260,"line":["c6b5","e4e5"]},"c3d5":{"score":260,"line":["c6d5","e4e5"]},"c3b1":{"score":85,"line":["d5e4","d3e4"]},"c3d1":{"score":88,"line":["d5e4"]},"a3a4":{"score":138,"line":["b5b4","c3d1"]},"a3a5":{"score":83,"line":["b5b4"]},"e4e5":{"score":-9,"line":["a7a6","g1f3"]},"e4d5":{"score":-50,"line":["e6d5","d3g3"]}},"bestMove":"d3c4"},"rn1qkb1r/pp2pppp/2p5/3pPb2/3P1Bn1/2N5/PPP2PPP/R2QKBNR w KQkq - 3 6":{"moves":{"g1e2":{"score":-158,"line":["h7h5"]},"g1f3":{"score":-89,"line":["e7e6","f1d3"]},"g1h3":{"score":-47,"line":["e7e6"]},"f1e2":{"score":-124,"line":["g4h6"]},"f1d3":{"score":-79,"line":["f5d3"]},"f1c4":{"score":364,"line":["d5c4"]},"f1b5":{"score":384,"line":["c6b5","f2f3"]},"f1a6":{"score":447,"line":["b8a6","f2f3"]},"e1e2":{"score":72,"line":["c6c5"]},"e1d2":{"score":462,"line":["g4f2","d1f3"]},"d1d2":{"score":-124,"line":["g4h6"]},"d1d3":{"score":798,"line":["f5d3","f1d3","d8b6","g1e2","e7e6","e1g1"]},"d1c1":{"score":-57,"line":["g4h6"]},"d1b1":{"score":-26,"line":["g4h6","f4h6"]},"d1e2":{"score":-119,"line":["h7h5","h2h3"]},"d1f3":{"score":-48,"line":["e7e6","h2h3","h7h5","e1c1","b8d7","c1b1"]},"d1g4":{"score":827,"line":["f5g4","g1f3"]},"a1b1":{"score":-73,"line":["e7e6","f1e2"]},"a1c1":{"score":-73,"line":["e7e6","f1e2"]},"h2h3":{"score":-118,"line":["g4h6","g2g4","f5d7","d1d2","e7e6","f4e3"]},"h2h4":{"score":-23,"line":["h7h5"]},"g2g3":{"score":-69,"line":["d8b6","c3a4"]},"f2f3":{"score":-66,"line":["g4h6"]},"b2b3":{"score":-18,"line":["e7e6"]},"b2b4":{"score":9,"line":["e7e6"]},"a2a3":{"score":-62,"line":["h7h5"]},"a2a4":{"score":-76,"line":["h7h5","h2h3"]},"c3a4":{"score":-81,"line":["h7h5","h2h3"]},"c3e4":{"score":345,"line":["d5e4"]},"c3e2":{"score":-70,"line":["d8b6"]},"c3b5":{"score":301,"line":["c6b5"]},"c3d5":{"score":268,"line":["c6d5","h2h3"]},"c3b1":{"score":35,"line":["d8b6","f4c1"]},"f4g3":{"score":-11,"line":["e7e6","g1f3"]},"f4e3":{"score":46,"line":["g4e3"]},"f4d2":{"score":-34,"line":["h7h5","g1f3"]},"f4c1":{"score":-26,"line":["e7e6"]},"f4g5":{"score":-61,"line":["f7f6","e5f6"]},"f4h6":{"score":511,"line":["g4h6","f1e2"]},"e5e6":{"score":92,"line":["f5e6","g1f3"]}},"bestMove":"d1g4"},"rn1qkb1r/pp2pppp/2p2n2/5b2/3P4/2N5/PPPQ1PPP/R1B1KBNR w KQkq - 5 7":{"moves":{"g1e2":{"score":73,"line":["e7e6"]},"g1f3":{"score":0,"line":["e7e6","f1d3"]},"g1h3":{"score":89,"line":["e7e6","f2f3"]},"f1e2":{"score":46,"line":["e7e6"]},"f1d3":{"score":4,"line":["f5d3","d2d3"]},"f1c4":{"score":53,"line":["e7e6"]},"f1b5":{"score":544,"line":["c6b5","c3b5"]},"f1a6":{"score":551,"line":["b8a6","a2a3"]},"e1e2":{"score":190,"line":["e7e6","e2e1"]},"e1d1":{"score":113,"line":["b8a6","f1a6"]},"a1b1":{"score":41,"line":["e7e6"]},"h2h3":{"score":32,"line":["e7e6"]},"h2h4":{"score":81,"line":["e7e6"]},"g2g3":{"score":66,"line":["e7e6","g1f3"]},"g2g4":{"score":166,"line":["f5g4"]},"f2f3":{"score":108,"line":["e7e6"]},"f2f4":{"score":91,"line":["e7e6","g1f3"]},"d2d3":{"score":878,"line":["f5d3","f1d3"]},"d2d1":{"score":38,"line":["e7e6"]},"d2e2":{"score":135,"line":["d8d4","c1d2"]},"d2e3":{"score":148,"line":["f5c2","g1f3"]},"d2f4":{"score":166,"line":["f5c2"]},"d2g5":{"score":146,"line":["f5c2","g1f3"]},"d2h6":{"score":1297,"line":["g7h6","g1f3"]},"b2b3":{"score":78,"line":["e7e6","a2a3"]},"b2b4":{"score":116,"line":["e7e6"]},"a2a3":{"score":35,"line":["e7e6","g1f3"]},"a2a4":{"score":60,"line":["e7e6"]},"c3a4":{"score":126,"line":["f6e4"]},"c3e4":{"score":532,"line":["f5e4","g1f3"]},"c3e2":{"score":42,"line":["e7e6"]},"c3b5":{"score":453,"line":["c6b5"]},"c3d5":{"score":516,"line":["c6d5","f1d3"]},"c3b1":{"score":69,"line":["e7e6","g1f3"]},"c3d1":{"score":61,"line":["e7e6"]},"d4d5":{"score":220,"line":["c6d5"]},"d4d6":{"score":172,"line":["d8d6"]}},"bestMove":"d2h6"},"r2qkbnr/pp1npp1p/2p3p1/5b2/3PN3/5Q2/PPPB1PPP/R3KBNR w KQkq - 2 7":{"moves":{"g1e2":{"score":29,"line":["f5e4","f3e4"]},"g1h3":{"score":23,"line":["g8f6","e4f6"]},"f1e2":{"score":61,"line":["d8b6","d2c3"]},"f1d3":{"score":-3,"line":["g8f6","e4f6"]},"f1c4":{"score":11,"line":["e7e6"]},"f1b5":{"score":505,"line":["c6b5","g1e2"]},"f1a6":{"score":444,"line":["b7a6"]},"e1e2":{"score":287,"line":["f8g7","e4g3"]},"e1d1":{"score":294,"line":["g8f6","e4f6"]},"e1c1":{"score":119,"line":["d7f6","e4f6"]},"a1b1":{"score":148,"line":["f8g7","g1e2"]},"a1c1":{"score":61,"line":["f8h6","d2h6"]},"a1d1":{"score":42,"line":["g8f6"]},"h2h3":{"score":62,"line":["d8b6","e1c1"]},"h2h4":{"score":57,"line":["d8b6"]},"g2g3":{"score":113,"line":["d8b6","f1h3"]},"g2g4":{"score":47,"line":["f5e4","f3e4"]},"d2c1":{"score":109,"line":["e7e5","d4e5"]},"d2c3":{"score":47,"line":["g8f6","f1d3"]},"d2b4":{"score":107,"line":["d8b6","b4c3"]},"d2a5":{"score":680,"line":["d8a5"]},"d2e3":{"score":108,"line":["d8b6"]},"d2f4":{"score":112,"line":["d8b6","e1c1","g8f6","e4f6","d7f6","f3b3"]},"d2g5":{"score":179,"line":["d8b6","e1c1"]},"d2h6":{"score":645,"line":["g8h6","h2h3"]},"c2c3":{"score":38,"line":["e7e5"]},"c2c4":{"score":81,"line":["f8g7"]},"b2b3":{"score":70,"line":["f8h6","d2h6"]},"b2b4":{"score":119,"line":["f8g7"]},"a2a3":{"score":76,"line":["f8g7","c2c3"]},"a2a4":{"score":27,"line":["g8f6","e4f6"]},"f3f4":{"score":167,"line":["f8h6","f4h4"]},"f3f5":{"score":796,"line":["g6f5","e4c3"]},"f3e3":{"score":75,"line":["f8h6"]},"f3d3":{"score":94,"line":["d8b6","e1c1"]},"f3c3":{"score":523,"line":["f5e4"]},"f3b3":{"score":396,"line":["f5e4","f2f3"]},"f3a3":{"score":509,"line":["f5e4","a3b3"]},"f3g3":{"score":533,"line":["f5e4"]},"f3h3":{"score":784,"line":["f5h3","g1h3"]},"f3e2":{"score":77,"line":["d8c7","e4g3"]},"f3d1":{"score":496,"line":["f5e4"]},"f3g4":{"score":1234,"line":["f5g4","f2f3"]},"f3h5":{"score":1204,"line":["g6h5","f1d3","f5e4","d3e4","d7f6","e4d3"]},"e4c5":{"score":119,"line":["d7c5"]},"e4g5":{"score":100,"line":["g8f6","f3b3"]},"e4c3":{"score":172,"line":["f5c2"]},"e4g3":{"score":9,"line":["f5e6"]},"e4d6":{"score":518,"line":["e7d6"]},"e4f6":{"score":557,"line":["g8f6"]},"d4d5":{"score":194,"line":["c6d5","e4g3"]},"d4d6":{"score":173,"line":["f8g7","d2c3"]}},"bestMove":"f3g4"},"r3kb1r/pp2pppp/2n2n2/q4b2/3P4/3BB3/PPP2PPP/RN1QK1NR w KQkq - 4 7":{"moves":{"e1e2":{"score":94,"line":["e7e5","d4e5"]},"e1f1":{"score":-3,"line":["c6b4"]},"d1d2":{"score":-18,"line":["a5d2","b1d2"]},"b1d2":{"score":73,"line":["c6b4","e1e2"]},"b1c3":{"score":-80,"line":["e7e6","d3f5"]},"c2c3":{"score":-73,"line":["f5d3","d1d3"]},"b2b4":{"score":251,"line":["c6b4"]},"e3d2":{"score":-78,"line":["a5d5"]}},"bestMove":"b2b4"},"rnbqkbnr/pp2pppp/8/3p4/3P4/8/PPP2PPP/RNBQKBNR w KQkq - 0 4":{"moves":{"g1e2":{"score":22,"line":["b8c6"]},"g1f3":{"score":0,"line":["b8c6","f1d3"]},"g1h3":{"score":75,"line":["c8h3"]},"f1e2":{"score":34,"line":["g8f6"]},"f1d3":{"score":15,"line":["b8c6"]},"f1c4":{"score":452,"line":["d5c4"]},"f1b5":{"score":0,"line":["c8d7","b5d3","b8c6","c2c3","e7e5","d4e5"]},"f1a6":{"score":512,"line":["b8a6"]},"e1e2":{"score":186,"line":["b8c6","e2e1"]},"e1d2":{"score":155,"line":["b8c6"]},"d1d2":{"score":35,"line":["g8f6","g1f3"]},"d1d3":{"score":34,"line":["b8c6"]},"d1e2":{"score":57,"line":["g8f6","g1f3"]},"d1f3":{"score":82,"line":["b8c6","f3d1"]},"d1g4":{"score":1259,"line":["c8g4","g1f3"]},"d1h5":{"score":88,"line":["b8c6"]},"c1d2":{"score":34,"line":["b8c6","g1f3"]},"c1e3":{"score":9,"line":["c8f5"]},"c1f4":{"score":18,"line":["b8c6","g1f3"]},"c1g5":{"score":18,"line":["b8c6","g1f3"]},"c1h6":{"score":513,"line":["g8h6"]},"b1d2":{"score":46,"line":["c8f5","d2f3"]},"b1a3":{"score":47,"line":["b8c6","c2c3"]},"b1c3":{"score":60,"line":["b8c6"]},"h2h3":{"score":-3,"line":["c8f5","c2c4"]},"h2h4":{"score":45,"line":["g8f6","c2c3"]},"g2g3":{"score":50,"line":["c8f5","g1f3"]},"g2g4":{"score":119,"line":["b8c6"]},"f2f3":{"score":80,"line":["b8c6","b1c3"]},"f2f4":{"score":105,"line":["b8c6","g1f3"]},"c2c3":{"score":16,"line":["c8f5","g1f3"]},"c2c4":{"score":3,"line":["e7e6","b1c3"]},"b2b3":{"score":61,"line":["b8c6"]},"b2b4":{"score":78,"line":["c8f5","f1d3"]},"a2a3":{"score":38,"line":["b8c6"]},"a2a4":{"score":46,"line":["b8c6"]}},"bestMove":"d1g4"},"rnbqkb1r/pp2pp1p/2p3p1/3n4/P2P4/2N5/1PP2PPP/R1BQKBNR w KQkq - 3 7":{"moves":{"g1e2":{"score":38,"line":["f8g7"]},"g1f3":{"score":-3,"line":["f8g7"]},"g1h3":{"score":83,"line":["f8g7"]},"f1e2":{"score":57,"line":["d5b4"]},"f1d3":{"score":-3,"line":["f8g7","c3d5"]},"f1c4":{"score":-9,"line":["c8e6","c4b3","d5c3","b2c3","e6b3","c2b3"]},"f1b5":{"score":520,"line":["d5c3","b2c3"]},"f1a6":{"score":516,"line":["b8a6","g1f3"]},"e1e2":{"score":206,"line":["f8g7","c3d5"]},"e1d2":{"score":232,"line":["d5b4"]},"d1d2":{"score":38,"line":["f8g7"]},"d1d3":{"score":124,"line":["d5b4","d3e2"]},"d1e2":{"score":86,"line":["f8g7"]},"d1f3":{"score":165,"line":["d5b4"]},"d1g4":{"score":1247,"line":["c8g4","c3d5"]},"d1h5":{"score":1195,"line":["g6h5","c3d5"]},"c1d2":{"score":57,"line":["f8g7"]},"c1e3":{"score":116,"line":["d5e3"]},"c1f4":{"score":536,"line":["d5f4","g2g3"]},"c1g5":{"score":25,"line":["f8g7","g1f3","h7h6","g5d2","e8g8","f1c4"]},"c1h6":{"score":563,"line":["d5c3","b2c3"]},"a1a2":{"score":221,"line":["d5b4","g1f3"]},"a1a3":{"score":97,"line":["e7e5"]},"a1b1":{"score":57,"line":["d5b4"]},"h2h3":{"score":30,"line":["d5b4"]},"h2h4":{"score":48,"line":["d5b4","c1e3"]},"g2g3":{"score":80,"line":["d5b4"]},"g2g4":{"score":155,"line":["d5b4"]},"f2f3":{"score":123,"line":["d5c3"]},"f2f4":{"score":109,"line":["d5b4","c1e3"]},"b2b3":{"score":563,"line":["d5c3","d1d3"]},"b2b4":{"score":506,"line":["d5c3","d1d2"]},"c3e4":{"score":11,"line":["f8g7"]},"c3a2":{"score":90,"line":["f8g7","g1f3"]},"c3e2":{"score":44,"line":["f8g7"]},"c3b5":{"score":310,"line":["c6b5"]},"c3d5":{"score":-4,"line":["c6d5"]},"c3b1":{"score":68,"line":["f8g7","g1f3"]},"a4a5":{"score":38,"line":["d5c3"]},"a4a6":{"score":3,"line":["b8a6","f1a6"]}},"bestMove":"d1g4"},"rnb1kbnr/ppq1pppp/8/2PpP3/8/8/PPP2PPP/RNBQKBNR w KQkq - 1 5":{"moves":{"g1e2":{"score":68,"line":["e7e6","c1e3"]},"g1f3":{"score":-93,"line":["e7e6"]},"g1h3":{"score":171,"line":["c8h3","g2h3"]},"f1e2":{"score":-3,"line":["e7e6","c2c4"]},"f1d3":{"score":57,"line":["c7e5"]},"f1c4":{"score":396,"line":["d5c4","g1f3"]},"f1b5":{"score":3,"line":["c8d7","b5d7"]},"f1a6":{"score":483,"line":["b8a6"]},"e1e2":{"score":297,"line":["c7e5","c1e3"]},"e1d2":{"score":211,"line":["c7e5","g1f3"]},"d1d2":{"score":22,"line":["c7e5"]},"d1d3":{"score":34,"line":["c7e5"]},"d1d4":{"score":39,"line":["e7e6","g1f3"]},"d1d5":{"score":-103,"line":["e7e6"]},"d1e2":{"score":30,"line":["e7e6"]},"d1f3":{"score":44,"line":["c7e5"]},"d1g4":{"score":1278,"line":["c8g4","f2f4"]},"d1h5":{"score":-3,"line":["e7e6"]},"c1d2":{"score":56,"line":["e7e6"]},"c1e3":{"score":-18,"line":["e7e6","g1f3"]},"c1f4":{"score":-83,"line":["e7e6"]},"c1g5":{"score":140,"line":["c7e5","g5e3"]},"c1h6":{"score":515,"line":["g8h6"]},"b1d2":{"score":49,"line":["c7e5","f1e2"]},"b1a3":{"score":3,"line":["e7e6","a3b5"]},"b1c3":{"score":-26,"line":["e7e6","c3b5"]},"h2h3":{"score":38,"line":["e7e6","g1f3"]},"h2h4":{"score":53,"line":["c7e5"]},"g2g3":{"score":43,"line":["e7e6","g1f3"]},"g2g4":{"score":148,"line":["c7e5"]},"f2f3":{"score":93,"line":["e7e6","f3f4"]},"f2f4":{"score":12,"line":["e7e6","c2c3"]},"c2c3":{"score":93,"line":["c7e5","f1e2"]},"c2c4":{"score":42,"line":["c7e5"]},"b2b3":{"score":494,"line":["c7e5"]},"b2b4":{"score":185,"line":["c7e5"]},"a2a3":{"score":-4,"line":["e7e6"]},"a2a4":{"score":42,"line":["c7e5"]},"e5e6":{"score":71,"line":["c8e6"]},"c5c6":{"score":152,"line":["c7e5"]}},"bestMove":"d1g4"},"rnbqkbnr/1p3ppp/p1p1p3/3pP3/3P4/8/PPP1BPPP/RNBQK1NR w KQkq - 0 5":{"moves":{"g1f3":{"score":-8,"line":["c6c5"]},"g1h3":{"score":53,"line":["c6c5"]},"e1f1":{"score":57,"line":["c6c5"]},"e1d2":{"score":226,"line":["c6c5","c2c3"]},"d1d2":{"score":15,"line":["c6c5"]},"d1d3":{"score":23,"line":["c6c5","c2c3"]},"c1d2":{"score":33,"line":["c6c5","c2c3"]},"c1e3":{"score":0,"line":["d8b6","g1f3","b6b2","b1d2","c6c5","c2c4"]},"c1f4":{"score":9,"line":["d8b6"]},"c1g5":{"score":526,"line":["d8g5"]},"c1h6":{"score":545,"line":["g8h6"]},"b1d2":{"score":-16,"line":["c6c5"]},"b1a3":{"score":0,"line":["d8a5"]},"b1c3":{"score":62,"line":["c6c5","g1f3"]},"h2h3":{"score":-4,"line":["c6c5"]},"h2h4":{"score":3,"line":["c6c5","c2c3"]},"g2g3":{"score":0,"line":["g8e7","g1f3"]},"g2g4":{"score":57,"line":["c6c5","c2c3"]},"f2f3":{"score":78,"line":["c6c5","c2c3"]},"f2f4":{"score":-8,"line":["c6c5"]},"e2f1":{"score":45,"line":["c6c5"]},"e2d3":{"score":-26,"line":["c6c5","c2c3"]},"e2c4":{"score":452,"line":["d5c4"]},"e2b5":{"score":528,"line":["a6b5"]},"e2a6":{"score":434,"line":["b8a6","c2c3"]},"e2f3":{"score":41,"line":["c6c5","c2c3"]},"e2g4":{"score":33,"line":["c6c5","c2c3"]},"e2h5":{"score":46,"line":["c6c5","c2c3"]},"c2c3":{"score":-16,"line":["g8e7"]},"c2c4":{"score":26,"line":["d5c4"]},"b2b3":{"score":4,"line":["c6c5","c2c3"]},"b2b4":{"score":103,"line":["f8b4","c2c3"]},"a2a3":{"score":-3,"line":["c6c5"]},"a2a4":{"score":-11,"line":["c6c5"]}},"bestMove":"c1h6"},"rnbqkbnr/pp3ppp/2p1p3/3p4/3PP3/2N5/PPP2PPP/R1BQKBNR w KQkq - 0 4":{"moves":{"g1e2":{"score":31,"line":["g8f6","e2g3"]},"g1f3":{"score":-4,"line":["f8b4"]},"g1h3":{"score":-10,"line":["g8e7","f1e2"]},"f1e2":{"score":-14,"line":["f8b4","d1d3"]},"f1d3":{"score":-4,"line":["d5e4"]},"f1c4":{"score":395,"line":["d5c4"]},"f1b5":{"score":478,"line":["c6b5","e4e5"]},"f1a6":{"score":496,"line":["b8a6"]},"e1e2":{"score":191,"line":["c6c5"]},"e1d2":{"score":216,"line":["d5e4"]},"d1d2":{"score":26,"line":["g8f6"]},"d1d3":{"score":-3,"line":["g8f6"]},"d1e2":{"score":8,"line":["g8f6"]},"d1f3":{"score":-21,"line":["g8f6","e4e5"]},"d1g4":{"score":91,"line":["g8f6","g4h4","d5e4","c1e3","f8b4","g1e2"]},"d1h5":{"score":95,"line":["g8f6"]},"c1d2":{"score":92,"line":["d5e4"]},"c1e3":{"score":-42,"line":["f8b4","e4e5"]},"c1f4":{"score":-3,"line":["g8f6","e4e5"]},"c1g5":{"score":457,"line":["d8g5","g1f3"]},"c1h6":{"score":516,"line":["g8h6","g1f3"]},"a1b1":{"score":-18,"line":["b7b5","a2a3"]},"h2h3":{"score":21,"line":["g8f6","f1d3"]},"h2h4":{"score":12,"line":["g8f6"]},"g2g3":{"score":12,"line":["f8b4","f1g2"]},"g2g4":{"score":56,"line":["g8f6","e4e5"]},"f2f3":{"score":26,"line":["f8b4"]},"f2f4":{"score":14,"line":["f8e7"]},"b2b3":{"score":54,"line":["f8b4","g1e2"]},"b2b4":{"score":240,"line":["f8b4"]},"a2a3":{"score":-15,"line":["g8f6"]},"a2a4":{"score":19,"line":["g8f6","f1d3"]},"c3a4":{"score":166,"line":["d5e4","c2c4"]},"c3e2":{"score":105,"line":["d5e4","e2g3"]},"c3b5":{"score":425,"line":["c6b5"]},"c3d5":{"score":350,"line":["e6d5","e4d5"]},"c3b1":{"score":177,"line":["d5e4","f1e2"]},"e4e5":{"score":42,"line":["c6c5"]},"e4d5":{"score":9,"line":["e6d5"]}},"bestMove":"c1h6"},"rn1qkbnr/1p3ppp/p1p1p3/3pPb2/1P1P4/N1P5/P4PPP/R1BQKBNR w KQkq - 0 7":{"moves":{"g1e2":{"score":70,"line":["a6a5","b4b5"]},"g1f3":{"score":-8,"line":["b8d7"]},"g1h3":{"score":85,"line":["a6a5","b4b5"]},"f1e2":{"score":-3,"line":["b7b5"]},"f1d3":{"score":10,"line":["g8e7"]},"f1c4":{"score":357,"line":["d5c4","a3c4"]},"f1b5":{"score":530,"line":["a6b5"]},"f1a6":{"score":438,"line":["b7a6"]},"e1e2":{"score":201,"line":["b8d7"]},"e1d2":{"score":217,"line":["a6a5","b4b5"]},"d1d2":{"score":86,"line":["a6a5"]},"d1d3":{"score":805,"line":["f5d3","f1d3","a6a5","a3c2","a5b4","c3b4"]},"d1c2":{"score":797,"line":["f5c2"]},"d1b3":{"score":109,"line":["f7f6"]},"d1a4":{"score":123,"line":["b8d7"]},"d1e2":{"score":100,"line":["b8d7"]},"d1f3":{"score":99,"line":["f5e4"]},"d1g4":{"score":1250,"line":["f5g4","f1e2"]},"d1h5":{"score":202,"line":["a6a5","b4b5"]},"c1b2":{"score":57,"line":["b8d7"]},"c1d2":{"score":81,"line":["a6a5"]},"c1e3":{"score":92,"line":["a6a5"]},"c1f4":{"score":96,"line":["a6a5"]},"c1g5":{"score":485,"line":["d8g5","g1f3"]},"c1h6":{"score":551,"line":["g8h6","a3c2"]},"a1b1":{"score":173,"line":["f5b1","a3b1"]},"h2h3":{"score":46,"line":["f5e4"]},"h2h4":{"score":-42,"line":["h7h6","a3c2"]},"g2g3":{"score":30,"line":["a6a5"]},"g2g4":{"score":130,"line":["f5e4"]},"f2f3":{"score":102,"line":["a6a5","b4b5"]},"f2f4":{"score":38,"line":["b8d7"]},"c3c4":{"score":437,"line":["f8b4"]},"c3c5":{"score":8,"line":["b7b6"]},"a3c4":{"score":400,"line":["d5c4"]},"a3c2":{"score":-15,"line":["b8d7","h2h4"]},"a3b5":{"score":479,"line":["a6b5","a2a4"]},"a3b1":{"score":27,"line":["g8e7","f1d3"]},"b4b5":{"score":244,"line":["d8a5"]},"b4b6":{"score":146,"line":["d8b6","a3c2"]}},"bestMove":"d1g4"},"rn1qkbnr/pp1b1pp1/4p2p/2ppP3/3P4/2PB4/PP1N1PPP/R1BQK1NR w KQkq - 1 7":{"moves":{"g1e2":{"score":-57,"line":["b8c6","e1g1"]},"g1f3":{"score":-19,"line":["c5d4"]},"g1h3":{"score":42,"line":["b8c6","e1g1"]},"e1e2":{"score":96,"line":["b8c6"]},"e1f1":{"score":-26,"line":["b8c6","g1e2"]},"d1c2":{"score":116,"line":["b8c6"]},"d1b3":{"score":190,"line":["c5c4","d2c4"]},"d1a4":{"score":1258,"line":["d7a4","g1e2","b8d7","b2b3","a4c6","d2f3"]},"d1e2":{"score":36,"line":["c5d4"]},"d1f3":{"score":34,"line":["b8c6"]},"d1g4":{"score":57,"line":["c5d4"]},"d1h5":{"score":38,"line":["c5d4","c3d4"]},"a1b1":{"score":73,"line":["c5d4","g1e2"]},"h2h3":{"score":-38,"line":["b8c6"]},"h2h4":{"score":-31,"line":["c5d4"]},"g2g3":{"score":-11,"line":["b8c6","g1e2"]},"g2g4":{"score":25,"line":["c5d4","c3d4"]},"f2f3":{"score":145,"line":["c5d4"]},"f2f4":{"score":-28,"line":["c5d4","c3d4"]},"d2b3":{"score":275,"line":["c5c4","d3c2"]},"d2f3":{"score":-30,"line":["c5d4","f3d4"]},"d2b1":{"score":53,"line":["b8c6"]},"d2f1":{"score":-22,"line":["b8c6","g1e2"]},"d2c4":{"score":450,"line":["d5c4"]},"d2e4":{"score":450,"line":["d5e4","d3c2"]},"b2b3":{"score":20,"line":["c5d4"]},"b2b4":{"score":113,"line":["c5d4","c3d4"]},"a2a3":{"score":-22,"line":["b8c6","g1e2"]},"a2a4":{"score":-34,"line":["b8c6","g1e2"]},"d3e2":{"score":-9,"line":["b8c6","g1f3"]},"d3f1":{"score":70,"line":["b8c6","d2b3"]},"d3c2":{"score":-9,"line":["c5d4","c3d4"]},"d3b1":{"score":7,"line":["c5d4","c3d4"]},"d3c4":{"score":442,"line":["d5c4"]},"d3b5":{"score":536,"line":["d7b5","g1e2"]},"d3a6":{"score":550,"line":["b8a6"]},"d3e4":{"score":496,"line":["d5e4"]},"d3f5":{"score":487,"line":["e6f5"]},"d3g6":{"score":481,"line":["f7g6"]},"d3h7":{"score":470,"line":["h8h7","g1e2"]},"c3c4":{"score":16,"line":["c5d4","c4d5"]},"d4c5":{"score":-61,"line":["a7a5","d1e2"]}},"bestMove":"d1a4"},"rnbqkbnr/pp2pppp/8/2p5/3P4/4P3/PPPNN1PP/R1BQKB1R w KQkq - 0 6":{"moves":{"h1g1":{"score":62,"line":["g8f6","d2f3"]},"e1f2":{"score":128,"line":["b8c6","d2f3"]},"a1b1":{"score":-9,"line":["c5d4","e2d4"]},"h2h3":{"score":16,"line":["c8d7","c2c3"]},"h2h4":{"score":103,"line":["g8f6","d2f3"]},"g2g3":{"score":-18,"line":["b8c6"]},"g2g4":{"score":88,"line":["c8g4"]},"e2c3":{"score":50,"line":["c5d4"]},"e2g3":{"score":45,"line":["c5d4","d2f3"]},"e2g1":{"score":73,"line":["c5d4","e3d4"]},"e2f4":{"score":99,"line":["c5d4"]},"d2b3":{"score":-26,"line":["c5d4","e3d4"]},"d2f3":{"score":11,"line":["g8f6"]},"d2b1":{"score":80,"line":["g8f6","c2c4"]},"d2c4":{"score":3,"line":["g7g6"]},"d2e4":{"score":-47,"line":["c5d4"]},"c2c3":{"score":-18,"line":["e7e5"]},"c2c4":{"score":8,"line":["c5d4"]},"b2b3":{"score":-22,"line":["g8f6","c1b2"]},"b2b4":{"score":3,"line":["c5b4"]},"a2a3":{"score":-9,"line":["c5d4","d2f3"]},"a2a4":{"score":47,"line":["g8f6","d2f3"]},"e3e4":{"score":84,"line":["c5d4"]},"e3e5":{"score":-3,"line":["b8c6","d2b3"]},"d4d5":{"score":33,"line":["g8f6","e3e4"]},"d4d6":{"score":134,"line":["e7d6","e2c3"]},"d4c5":{"score":-18,"line":["g8f6","e2c3"]}},"bestMove":"d4d6"},"r2qkbnr/pp2pppp/2n5/5b2/3P4/8/PPP2PPP/RNBQKBNR w KQkq - 0 5":{"moves":{"g1e2":{"score":4,"line":["g8f6","c1e3"]},"g1f3":{"score":-107,"line":["g8f6"]},"g1h3":{"score":137,"line":["d8d4"]},"f1e2":{"score":69,"line":["d8d4","c2c3"]},"f1d3":{"score":19,"line":["d8d4","g1f3"]},"f1c4":{"score":62,"line":["d8d4","d1e2"]},"f1b5":{"score":8,"line":["d8d5"]},"f1a6":{"score":450,"line":["d8a5"]},"e1e2":{"score":734,"line":["c6d4","e2e1"]},"e1d2":{"score":295,"line":["d8a5"]},"d1d2":{"score":46,"line":["c6d4"]},"d1d3":{"score":765,"line":["f5d3","f1d3"]},"d1e2":{"score":198,"line":["c6d4","e2d2"]},"d1f3":{"score":21,"line":["c6d4"]},"d1g4":{"score":1142,"line":["f5g4","c2c3"]},"d1h5":{"score":96,"line":["g7g6"]},"c1d2":{"score":62,"line":["d8d4","b1c3"]},"c1e3":{"score":-77,"line":["g8f6","f1d3"]},"c1f4":{"score":53,"line":["d8d4"]},"c1g5":{"score":85,"line":["d8d4","b1c3"]},"c1h6":{"score":523,"line":["g8h6"]},"b1d2":{"score":46,"line":["d8d4"]},"b1a3":{"score":36,"line":["e7e5"]},"b1c3":{"score":43,"line":["d8d4"]},"h2h3":{"score":100,"line":["d8d4"]},"h2h4":{"score":100,"line":["d8d4","d1d4"]},"g2g3":{"score":112,"line":["d8d4"]},"g2g4":{"score":16,"line":["f5e6","f1g2"]},"f2f3":{"score":100,"line":["e7e5"]},"f2f4":{"score":101,"line":["d8d4","d1d4"]},"c2c3":{"score":-119,"line":["g8f6","g1f3"]},"c2c4":{"score":140,"line":["c6d4"]},"b2b3":{"score":96,"line":["d8d4"]},"b2b4":{"score":99,"line":["d8d4","d1d4"]},"a2a3":{"score":81,"line":["d8d4"]},"a2a4":{"score":85,"line":["d8d4","f1e2"]},"d4d5":{"score":-57,"line":["d8a5","b1c3"]},"d4d6":{"score":82,"line":["e7e5","b1c3"]}},"bestMove":"d1g4"},"rnbqk1nr/pp2ppbp/6p1/3p4/3P4/5N2/PPPN1PPP/R1BQKB1R w KQkq - 0 6":{"moves":{"h1g1":{"score":160,"line":["g8f6"]},"f1e2":{"score":-9,"line":["g8f6","c2c3"]},"f1d3":{"score":-7,"line":["g8h6","e1g1"]},"f1c4":{"score":396,"line":["d5c4","d2c4"]},"f1b5":{"score":-30,"line":["c8d7","b5d3"]},"f1a6":{"score":501,"line":["b8a6","e1g1"]},"e1e2":{"score":163,"line":["b8c6","d2b3"]},"d1e2":{"score":64,"line":["b8c6"]},"a1b1":{"score":47,"line":["b8c6","d2b3"]},"h2h3":{"score":-1,"line":["g8f6","f1d3","b8c6","e1g1","e8g8","c2c3"]},"h2h4":{"score":33,"line":["b8c6"]},"g2g3":{"score":-10,"line":["b8c6","f1g2"]},"g2g4":{"score":190,"line":["c8g4","c2c3"]},"d2b3":{"score":3,"line":["b8c6"]},"d2b1":{"score":37,"line":["c8f5","f1d3"]},"d2c4":{"score":342,"line":["d5c4"]},"d2e4":{"score":539,"line":["d5e4"]},"c2c3":{"score":-26,"line":["b8c6","f1d3"]},"c2c4":{"score":93,"line":["g8f6","f3e5"]},"b2b3":{"score":42,"line":["c8f5","f1b5"]},"b2b4":{"score":85,"line":["c8f5","a2a4"]},"a2a3":{"score":22,"line":["b8c6"]},"a2a4":{"score":8,"line":["c8f5"]},"f3h4":{"score":204,"line":["g7d4"]},"f3e5":{"score":36,"line":["a7a6"]},"f3g5":{"score":171,"line":["e7e5","h2h4"]},"f3g1":{"score":214,"line":["g7d4","g1f3"]}},"bestMove":"d2e4"},"rn1qkb1r/1p1bnppp/p1p1p3/3pP3/3P4/2P4P/PP2BPP1/RNBQK1NR w KQkq - 0 7":{"moves":{"h1h2":{"score":145,"line":["c6c5","g1f3"]},"g1f3":{"score":7,"line":["c6c5"]},"e1f1":{"score":48,"line":["c6c5"]},"e1d2":{"score":150,"line":["c6c5","d2e1"]},"d1d2":{"score":57,"line":["c6c5"]},"d1d3":{"score":47,"line":["c6c5","g1f3"]},"d1c2":{"score":21,"line":["c6c5","g1f3"]},"d1b3":{"score":48,"line":["c6c5"]},"d1a4":{"score":57,"line":["c6c5"]},"c1d2":{"score":52,"line":["c6c5"]},"c1e3":{"score":30,"line":["c6c5"]},"c1f4":{"score":23,"line":["c6c5","g1f3"]},"c1g5":{"score":16,"line":["c6c5","g1f3"]},"c1h6":{"score":474,"line":["g7h6","b1d2"]},"b1d2":{"score":-4,"line":["c6c5","e2d3"]},"b1a3":{"score":22,"line":["c6c5"]},"g2g3":{"score":27,"line":["c6c5","g1f3"]},"g2g4":{"score":101,"line":["c6c5"]},"f2f3":{"score":156,"line":["e7f5"]},"f2f4":{"score":62,"line":["e7f5","g1f3"]},"e2f1":{"score":50,"line":["c6c5"]},"e2d3":{"score":0,"line":["c6c5"]},"e2c4":{"score":400,"line":["d5c4","b1d2"]},"e2b5":{"score":547,"line":["a6b5"]},"e2a6":{"score":402,"line":["b8a6"]},"e2f3":{"score":81,"line":["c6c5"]},"e2g4":{"score":57,"line":["c6c5","g4e2"]},"e2h5":{"score":85,"line":["c6c5","h5e2"]},"b2b3":{"score":45,"line":["c6c5"]},"b2b4":{"score":46,"line":["a6a5"]},"a2a3":{"score":12,"line":["c6c5","g1f3"]},"a2a4":{"score":26,"line":["c6c5"]},"h3h4":{"score":0,"line":["c6c5","g1f3"]},"h3h5":{"score":-22,"line":["c6c5","g1f3"]},"c3c4":{"score":57,"line":["d5c4","g1f3"]},"c3c5":{"score":-26,"line":["b7b6","d1b3"]}},"bestMove":"e2b5"},"r1bqk2r/pp1nppbp/5np1/1BPp4/4P3/7P/PPPNQPP1/R1B1K1NR w KQkq - 5 8":{"moves":{"h1h2":{"score":289,"line":["d5e4","b5d7"]},"g1f3":{"score":31,"line":["d5e4","f3g5"]},"e1d1":{"score":349,"line":["d5e4"]},"e1f1":{"score":190,"line":["d5e4","d2e4"]},"a1b1":{"score":113,"line":["d5e4"]},"g2g3":{"score":214,"line":["d5e4","d2c4"]},"g2g4":{"score":207,"line":["d5e4","d2b3"]},"f2f3":{"score":111,"line":["e8g8","e2e3"]},"f2f4":{"score":179,"line":["d5e4","d2e4"]},"e2e3":{"score":84,"line":["d5e4"]},"e2f1":{"score":189,"line":["d5e4"]},"e2d1":{"score":189,"line":["f6e4","d2e4"]},"e2d3":{"score":161,"line":["d5e4","d3e3"]},"e2c4":{"score":1196,"line":["d5c4","c5c6"]},"e2f3":{"score":147,"line":["e8g8"]},"e2g4":{"score":890,"line":["f6g4"]},"e2h5":{"score":1206,"line":["f6h5"]},"d2b3":{"score":142,"line":["f6e4","c5c6"]},"d2f3":{"score":295,"line":["f6e4"]},"d2b1":{"score":249,"line":["f6e4","g1f3"]},"d2f1":{"score":302,"line":["f6e4"]},"d2c4":{"score":419,"line":["d5c4","b5c4"]},"c2c3":{"score":23,"line":["d5e4","d2e4"]},"c2c4":{"score":88,"line":["d5e4"]},"b2b3":{"score":258,"line":["f6e4","d2e4","g7a1","e4d6","e8f8","d6c8"]},"b2b4":{"score":214,"line":["f6e4","d2e4"]},"a2a3":{"score":88,"line":["f6e4"]},"a2a4":{"score":22,"line":["a7a6"]},"h3h4":{"score":138,"line":["d5e4","h4h5"]},"h3h5":{"score":81,"line":["f6h5"]},"e4e5":{"score":-35,"line":["f6e4"]},"e4e6":{"score":3,"line":["f7e6","c5c6"]},"e4d5":{"score":0,"line":["f6d5","d2b3","e8g8","g1f3","d8c7","e1g1"]},"c5c6":{"score":-46,"line":["b7c6","b5c6"]},"c5c7":{"score":125,"line":["d8c7"]},"b5c4":{"score":497,"line":["d5c4","d2c4"]},"b5d3":{"score":106,"line":["d5e4"]},"b5a4":{"score":167,"line":["d5e4","a4d7"]},"b5a6":{"score":512,"line":["b7a6"]},"b5c6":{"score":554,"line":["b7c6"]},"b5d7":{"score":62,"line":["f6d7","g1f3"]}},"bestMove":"e2h5"},"rnb1kb1r/pp2pppp/2p2n2/q7/3Pp3/2N5/PPPBNPPP/R2QKB1R w KQkq - 0 6":{"moves":{"h1g1":{"score":142,"line":["a5b6","c3a4"]},"d1c1":{"score":128,"line":["a5d8"]},"d1b1":{"score":159,"line":["a5b6","a2a4","a7a5","d2e3","c8f5","d4d5"]},"a1b1":{"score":144,"line":["a5d8"]},"a1c1":{"score":110,"line":["a5b6"]},"h2h3":{"score":50,"line":["a5b6","g2g4"]},"h2h4":{"score":109,"line":["a5b6"]},"g2g3":{"score":85,"line":["a5b6","a2a4"]},"g2g4":{"score":187,"line":["c8g4","c3e4"]},"f2f3":{"score":201,"line":["e4f3"]},"f2f4":{"score":217,"line":["e4f3","g2f3"]},"e2g3":{"score":0,"line":["a5b6","c3e4","b6d4","f1d3","f6d5","e1g1"]},"e2c1":{"score":118,"line":["a5d8","d1e2"]},"e2g1":{"score":175,"line":["a5b6","g1e2"]},"e2f4":{"score":160,"line":["a5b6"]},"d2c1":{"score":169,"line":["c8f5","e2g3"]},"d2e3":{"score":155,"line":["c8f5","d1d2"]},"d2f4":{"score":109,"line":["c8f5","d1d2"]},"d2g5":{"score":633,"line":["a5g5","h2h4"]},"d2h6":{"score":519,"line":["g7h6"]},"b2b3":{"score":145,"line":["a5d8"]},"b2b4":{"score":142,"line":["a5d8"]},"a2a3":{"score":112,"line":["a5b6"]},"a2a4":{"score":91,"line":["a5d8","d2g5"]},"c3a4":{"score":566,"line":["a5a4"]},"c3e4":{"score":-38,"line":["a5d8"]},"c3b5":{"score":602,"line":["a5b5","d1c1"]},"c3d5":{"score":584,"line":["a5d5","d2e3"]},"c3b1":{"score":182,"line":["a5b6"]},"d4d5":{"score":136,"line":["a5b6","d2e3"]},"d4d6":{"score":151,"line":["e4e3","d2e3"]}},"bestMove":"d2g5"},"rn1qkbnr/1p3ppp/4p3/p1PpPb2/1P6/N7/P1P2PPP/R1BQKBNR w KQkq a6 0 7":{"moves":{"g1e2":{"score":199,"line":["a5b4","a3b5"]},"g1f3":{"score":163,"line":["a5b4","a3b5"]},"g1h3":{"score":287,"line":["a5b4","a3b5"]},"f1e2":{"score":214,"line":["a5b4","a3b5"]},"f1d3":{"score":109,"line":["a5b4","d3f5"]},"f1c4":{"score":458,"line":["d5c4","d1d8"]},"f1b5":{"score":43,"line":["b8c6","c2c3"]},"f1a6":{"score":683,"line":["b8a6"]},"e1e2":{"score":421,"line":["a5b4"]},"e1d2":{"score":405,"line":["a5b4","a3b5"]},"d1d2":{"score":150,"line":["a5b4","d2b4"]},"d1d3":{"score":892,"line":["f5d3","f1d3"]},"d1d4":{"score":227,"line":["b8c6","f1b5","a5b4","d4b4","d8a5","b4a5"]},"d1d5":{"score":1196,"line":["d8d5","g1f3"]},"d1e2":{"score":237,"line":["a5b4","a3b5"]},"d1f3":{"score":291,"line":["b8c6","f3g3"]},"d1g4":{"score":1303,"line":["f5g4","h2h3"]},"d1h5":{"score":299,"line":["a5b4","a3b5"]},"c1b2":{"score":224,"line":["a5b4"]},"c1d2":{"score":250,"line":["a5b4","a3b5"]},"c1e3":{"score":80,"line":["a5b4"]},"c1f4":{"score":185,"line":["a5b4"]},"c1g5":{"score":429,"line":["d8g5"]},"c1h6":{"score":792,"line":["g8h6","a3b5"]},"a1b1":{"score":220,"line":["a5b4"]},"h2h3":{"score":220,"line":["a5b4","a3b5"]},"h2h4":{"score":46,"line":["a5b4"]},"g2g3":{"score":281,"line":["a5b4"]},"g2g4":{"score":197,"line":["f5e4"]},"f2f3":{"score":395,"line":["a5b4"]},"f2f4":{"score":357,"line":["a5b4","a3b5"]},"c2c3":{"score":0,"line":["a5b4","c3b4","b8c6","f1b5","d8h4","d1d2"]},"c2c4":{"score":178,"line":["a5b4"]},"a3c4":{"score":505,"line":["d5c4","d1d8"]},"a3b5":{"score":0,"line":["a5b4","b5d6","f8d6","c5d6","b8c6","g1f3"]},"a3b1":{"score":225,"line":["a5b4","f1d3"]},"b4b5":{"score":272,"line":["f8c5"]},"b4b6":{"score":220,"line":["f8c5"]},"b4a5":{"score":156,"line":["f8c5"]},"c5c6":{"score":416,"line":["f8b4"]},"c5c7":{"score":334,"line":["d8c7"]}},"bestMove":"d1g4"},"rn1qkbnr/1p3ppp/p3p3/2ppPb2/3P4/5N2/PPP1BPPP/RNBQ1RK1 w kq - 0 7":{"moves":{"g1h1":{"score":32,"line":["b8c6","c2c3","f5g6","a2a3","c5d4","c3d4"]},"f1e1":{"score":39,"line":["b8c6","c2c3"]},"d1d2":{"score":61,"line":["b8c6"]},"d1d3":{"score":834,"line":["f5d3"]},"d1e1":{"score":69,"line":["b8d7"]},"c1d2":{"score":44,"line":["d8b6"]},"c1e3":{"score":-18,"line":["c5d4"]},"c1f4":{"score":50,"line":["b8c6"]},"c1g5":{"score":9,"line":["d8b6"]},"c1h6":{"score":562,"line":["g8h6"]},"b1d2":{"score":9,"line":["b8c6"]},"b1a3":{"score":22,"line":["b8c6"]},"b1c3":{"score":58,"line":["b8c6","c1e3","c5d4","f3d4","c6d4","e3d4"]},"h2h3":{"score":23,"line":["c5d4","f3d4"]},"h2h4":{"score":60,"line":["b8c6"]},"g2g3":{"score":58,"line":["b8c6","c2c3"]},"g2g4":{"score":160,"line":["f5g4"]},"e2d3":{"score":27,"line":["f5d3","c2d3"]},"e2c4":{"score":500,"line":["d5c4"]},"e2b5":{"score":505,"line":["a6b5","b1c3"]},"e2a6":{"score":453,"line":["b8a6"]},"c2c3":{"score":-16,"line":["b8d7"]},"c2c4":{"score":-8,"line":["d5c4","c1g5"]},"b2b3":{"score":45,"line":["c5d4"]},"b2b4":{"score":72,"line":["c5b4"]},"a2a3":{"score":10,"line":["c5d4"]},"a2a4":{"score":42,"line":["b8c6"]},"f3h4":{"score":495,"line":["d8h4"]},"f3d2":{"score":110,"line":["c5d4","d2f3","b8c6","f3d4","c6d4","d1d4"]},"f3g5":{"score":113,"line":["c5d4","g5f3"]},"f3e1":{"score":124,"line":["c5d4","d1d4"]},"d4c5":{"score":33,"line":["f8c5"]}},"bestMove":"d1d3"},"rnbqkbnr/pp2pppp/8/2ppP3/3P4/8/PPP2PPP/RNBQKBNR w KQkq - 0 4":{"moves":{"g1e2":{"score":30,"line":["c5d4"]},"g1f3":{"score":42,"line":["c5d4","f3d4"]},"g1h3":{"score":181,"line":["c8h3","g2h3"]},"f1e2":{"score":72,"line":["c5d4"]},"f1d3":{"score":62,"line":["c5d4","c1f4"]},"f1c4":{"score":489,"line":["d5c4","g1f3"]},"f1b5":{"score":30,"line":["c8d7"]},"f1a6":{"score":509,"line":["b8a6","c2c3"]},"e1e2":{"score":245,"line":["c5d4","f2f4"]},"e1d2":{"score":266,"line":["b8c6","c2c3"]},"d1d2":{"score":97,"line":["c5d4","d2d4"]},"d1d3":{"score":78,"line":["c5d4","d3d4"]},"d1e2":{"score":142,"line":["c5d4","b1d2"]},"d1f3":{"score":95,"line":["c5d4"]},"d1g4":{"score":1283,"line":["c8g4"]},"d1h5":{"score":109,"line":["c5d4","f1d3"]},"c1d2":{"score":109,"line":["c5d4","g1f3"]},"c1e3":{"score":27,"line":["c5d4","e3d4"]},"c1f4":{"score":45,"line":["c5d4"]},"c1g5":{"score":96,"line":["c5d4","g1e2"]},"c1h6":{"score":535,"line":["g8h6"]},"b1d2":{"score":44,"line":["c5d4"]},"b1a3":{"score":12,"line":["b8c6","c2c3"]},"b1c3":{"score":38,"line":["b8c6"]},"h2h3":{"score":61,"line":["c5d4"]},"h2h4":{"score":85,"line":["c5d4","c2c3"]},"g2g3":{"score":125,"line":["c5d4","f1g2"]},"g2g4":{"score":201,"line":["c5d4"]},"f2f3":{"score":76,"line":["c5d4","f3f4"]},"f2f4":{"score":38,"line":["c5d4","b1d2"]},"c2c3":{"score":-21,"line":["b8c6"]},"c2c4":{"score":14,"line":["c5d4"]},"b2b3":{"score":93,"line":["c5d4","d1d4"]},"b2b4":{"score":93,"line":["c5d4","d1d4"]},"a2a3":{"score":94,"line":["c5d4"]},"a2a4":{"score":50,"line":["c5d4","g1e2"]},"d4c5":{"score":-3,"line":["e7e6","g1f3"]},"e5e6":{"score":137,"line":["c8e6"]}},"bestMove":"d1g4"},"rnbqk2r/pp2ppbp/2p2np1/8/3PN3/6N1/PPP2PPP/R1BQKB1R w KQkq - 3 7":{"moves":{"h1g1":{"score":200,"line":["b8d7"]},"f1e2":{"score":131,"line":["f6e4","g3e4"]},"f1d3":{"score":118,"line":["d8d4","c2c3"]},"f1c4":{"score":76,"line":["f6e4","g3e4"]},"f1b5":{"score":539,"line":["f6e4"]},"f1a6":{"score":555,"line":["b8a6"]},"e1e2":{"score":193,"line":["b8d7"]},"e1d2":{"score":346,"line":["f6e4"]},"d1d2":{"score":159,"line":["f6e4","g3e4"]},"d1d3":{"score":130,"line":["f6e4"]},"d1e2":{"score":140,"line":["d8d4","c2c3"]},"d1f3":{"score":132,"line":["d8d4","e4f6"]},"d1g4":{"score":1242,"line":["f6g4"]},"d1h5":{"score":1183,"line":["f6h5"]},"c1d2":{"score":224,"line":["f6e4"]},"c1e3":{"score":66,"line":["f6d5","f1c4"]},"c1f4":{"score":93,"line":["f6e4","g3e4"]},"c1g5":{"score":130,"line":["f6e4"]},"c1h6":{"score":547,"line":["g7h6"]},"a1b1":{"score":174,"line":["f6e4"]},"h2h3":{"score":123,"line":["f6e4"]},"h2h4":{"score":97,"line":["f6e4","g3e4"]},"f2f3":{"score":104,"line":["f6e4"]},"f2f4":{"score":144,"line":["f6e4","g3e4"]},"c2c3":{"score":8,"line":["f6e4"]},"c2c4":{"score":190,"line":["f6e4","g3e4","d8d4","d1d4","g7d4","f1e2"]},"b2b3":{"score":263,"line":["f6e4"]},"b2b4":{"score":259,"line":["f6e4"]},"a2a3":{"score":119,"line":["f6e4"]},"a2a4":{"score":97,"line":["f6e4","g3e4"]},"g3e2":{"score":516,"line":["f6e4"]},"g3f5":{"score":540,"line":["c8f5","e4g3"]},"g3h5":{"score":497,"line":["f6h5","c2c3"]},"e4c5":{"score":108,"line":["b7b6"]},"e4g5":{"score":100,"line":["c6c5","f1c4"]},"e4c3":{"score":83,"line":["e8g8"]},"e4d6":{"score":534,"line":["d8d6"]},"e4f6":{"score":34,"line":["e7f6","f1c4"]},"e4d2":{"score":190,"line":["d8d4","c2c3"]},"d4d5":{"score":263,"line":["f6e4"]},"d4d6":{"score":159,"line":["f6e4","g3e4"]}},"bestMove":"d1g4"},"rnbqk2r/pp3ppp/4pn2/3p4/1b1P4/2NQ1N2/PPP2PPP/R1B1KB1R w KQkq - 0 7":{"moves":{"h1g1":{"score":92,"line":["f6e4","c1d2"]},"f1e2":{"score":26,"line":["b8c6"]},"e1e2":{"score":188,"line":["e8g8","a2a3"]},"e1d1":{"score":196,"line":["b8c6","a2a3"]},"e1d2":{"score":202,"line":["e8g8","d2e1"]},"c1d2":{"score":74,"line":["b8c6","f3e5"]},"c1e3":{"score":73,"line":["f6e4"]},"c1f4":{"score":54,"line":["f6e4","f3d2"]},"c1g5":{"score":35,"line":["b8c6","a2a3"]},"c1h6":{"score":468,"line":["g7h6"]},"a1b1":{"score":69,"line":["e8g8"]},"h2h3":{"score":73,"line":["b8c6"]},"h2h4":{"score":50,"line":["b8c6"]},"g2g3":{"score":73,"line":["f6e4"]},"g2g4":{"score":77,"line":["f6e4"]},"b2b3":{"score":210,"line":["f6e4"]},"a2a3":{"score":35,"line":["b4a5","f1e2"]},"a2a4":{"score":73,"line":["b8c6","f3e5"]},"f3h4":{"score":117,"line":["f6e4","h4f3"]},"f3d2":{"score":96,"line":["e8g8","f1e2"]},"f3e5":{"score":53,"line":["b8c6"]},"f3g5":{"score":103,"line":["b8c6"]},"f3g1":{"score":82,"line":["b8c6","g1f3"]},"d3d2":{"score":83,"line":["f6e4","d2e3"]},"d3d1":{"score":69,"line":["f6e4","c1d2"]},"d3e3":{"score":38,"line":["b8c6"]},"d3e2":{"score":99,"line":["e8g8","c1g5"]},"d3c4":{"score":1169,"line":["d5c4","f1c4"]},"d3b5":{"score":58,"line":["b8c6","a2a3"]},"d3a6":{"score":1253,"line":["b7a6"]},"d3e4":{"score":1351,"line":["d5e4","f3d2"]},"d3f5":{"score":1252,"line":["b4c3"]},"d3g6":{"score":1290,"line":["h7g6","f1b5"]},"d3h7":{"score":1165,"line":["f6h7","a2a3"]}},"bestMove":"d3e4"},"r1bqkbnr/pp2pppp/2p2n2/8/3PNB2/8/PPP2PPP/R2QKBNR w KQkq - 3 6":{"moves":{"g1e2":{"score":481,"line":["f6e4"]},"g1f3":{"score":390,"line":["f6e4","f1d3"]},"g1h3":{"score":516,"line":["f6e4"]},"f1e2":{"score":396,"line":["f6e4","g1f3"]},"f1d3":{"score":105,"line":["d8d4","g1f3"]},"f1c4":{"score":411,"line":["f6e4"]},"f1b5":{"score":512,"line":["c6b5"]},"f1a6":{"score":516,"line":["f6e4","a6c4"]},"e1e2":{"score":539,"line":["f6e4"]},"e1d2":{"score":670,"line":["d8d4","d2c1"]},"d1d2":{"score":528,"line":["f6e4"]},"d1d3":{"score":122,"line":["f6e4"]},"d1c1":{"score":460,"line":["f6e4","g1f3"]},"d1b1":{"score":444,"line":["f6e4","c2c3","e4d6","f1d3","g8f6","h2h3"]},"d1e2":{"score":101,"line":["f6e4","e2e4"]},"d1f3":{"score":148,"line":["d8d4","e4c3"]},"d1g4":{"score":1215,"line":["c8g4"]},"d1h5":{"score":1242,"line":["f6h5"]},"a1b1":{"score":453,"line":["f6e4"]},"a1c1":{"score":476,"line":["f6e4"]},"h2h3":{"score":454,"line":["f6e4","g1f3"]},"h2h4":{"score":488,"line":["f6e4"]},"g2g3":{"score":414,"line":["f6e4"]},"g2g4":{"score":550,"line":["f6e4","c2c3"]},"f2f3":{"score":82,"line":["d8b6","c2c3"]},"c2c3":{"score":426,"line":["f6e4"]},"c2c4":{"score":513,"line":["f6e4","a2a3"]},"b2b3":{"score":547,"line":["f6e4"]},"b2b4":{"score":542,"line":["f6e4","a2a3"]},"a2a3":{"score":465,"line":["f6e4","c2c3"]},"a2a4":{"score":439,"line":["f6e4"]},"f4g3":{"score":493,"line":["f6e4","c2c3"]},"f4e3":{"score":431,"line":["f6e4","f1d3"]},"f4d2":{"score":479,"line":["f6e4","d2e3","g8f6","f1d3","d8b6","d1b1"]},"f4c1":{"score":450,"line":["f6e4"]},"f4e5":{"score":435,"line":["f6e4","f1d3"]},"f4d6":{"score":557,"line":["e7d6","e4f6"]},"f4c7":{"score":526,"line":["d8c7","e4d2","c8f5","g1f3","e7e6","c2c3"]},"f4b8":{"score":545,"line":["a8b8"]},"f4g5":{"score":496,"line":["f6e4"]},"f4h6":{"score":520,"line":["g8h6","e4f6"]},"e4c5":{"score":8,"line":["b7b6","c5b3"]},"e4g5":{"score":34,"line":["c8f5"]},"e4c3":{"score":8,"line":["c8f5"]},"e4g3":{"score":-4,"line":["h7h5"]},"e4d6":{"score":493,"line":["e7d6","f1d3"]},"e4f6":{"score":-15,"line":["g8f6","g1f3"]},"e4d2":{"score":183,"line":["d8d4","f4g3"]},"d4d5":{"score":471,"line":["f6e4"]},"d4d6":{"score":585,"line":["f6e4"]}},"bestMove":"d1h5"},"rnb1kbnr/pp2pppp/2p5/3q4/3P4/8/PPP2PPP/RNBQKBNR w KQkq - 0 4":{"moves":{"g1e2":{"score":-30,"line":["g8f6","b1c3"]},"g1f3":{"score":-64,"line":["c8f5","c2c4","d5d8","f1d3","f5d3","d1d3"]},"g1h3":{"score":413,"line":["c8h3","c2c4","d5e4","c1e3","h3f5","b1c3"]},"f1e2":{"score":112,"line":["d5g2"]},"f1d3":{"score":156,"line":["d5g2"]},"f1c4":{"score":460,"line":["d5c4","g1e2"]},"f1b5":{"score":568,"line":["d5g2","d1f3","g2f3","g1f3","c6b5","b1c3"]},"f1a6":{"score":676,"line":["d5g2","d1f3"]},"e1e2":{"score":195,"line":["e7e5"]},"e1d2":{"score":220,"line":["d5d4","d2e1"]},"d1d2":{"score":17,"line":["e7e5","g1f3","e5d4","d2d4","d5d4","f3d4"]},"d1d3":{"score":117,"line":["c8f5"]},"d1e2":{"score":69,"line":["d5d4","g1f3"]},"d1f3":{"score":127,"line":["d5d4","f3e2"]},"d1g4":{"score":1257,"line":["c8g4"]},"d1h5":{"score":1230,"line":["d5h5"]},"c1d2":{"score":101,"line":["d5d4","b1c3"]},"c1e3":{"score":-53,"line":["c8f5","g1f3"]},"c1f4":{"score":-61,"line":["c8f5","c2c4"]},"c1g5":{"score":461,"line":["d5g5"]},"c1h6":{"score":513,"line":["g8h6","g1f3"]},"b1d2":{"score":88,"line":["d5d4"]},"b1a3":{"score":9,"line":["e7e5"]},"b1c3":{"score":-26,"line":["d5d8"]},"h2h3":{"score":-19,"line":["e7e5"]},"h2h4":{"score":-19,"line":["e7e5"]},"g2g3":{"score":776,"line":["d5h1"]},"g2g4":{"score":804,"line":["d5h1","g1e2"]},"f2f3":{"score":-3,"line":["e7e5"]},"f2f4":{"score":33,"line":["g7g6"]},"c2c3":{"score":-29,"line":["e7e5"]},"c2c4":{"score":-54,"line":["d5a5"]},"b2b3":{"score":31,"line":["c8f5","b1c3"]},"b2b4":{"score":62,"line":["e7e5","g1f3"]},"a2a3":{"score":-27,"line":["d5a5"]},"a2a4":{"score":-9,"line":["e7e5","g1f3"]}},"bestMove":"d1g4"},"rnb1kbnr/pp3ppp/2p1p3/8/3qN3/3B4/PPP2PPP/R1BQK1NR w KQkq - 0 6":{"moves":{"g1e2":{"score":73,"line":["d4d8"]},"g1f3":{"score":34,"line":["d4d8"]},"g1h3":{"score":78,"line":["b8d7","c2c3"]},"e1e2":{"score":105,"line":["f7f5","g1f3"]},"e1f1":{"score":97,"line":["g8f6","g1f3"]},"e1d2":{"score":208,"line":["f7f5","g1f3"]},"d1d2":{"score":105,"line":["g8f6","e4f6"]},"d1e2":{"score":30,"line":["g8f6"]},"d1f3":{"score":83,"line":["f7f5"]},"d1g4":{"score":373,"line":["f7f5","g4h5"]},"d1h5":{"score":95,"line":["f8b4"]},"c1d2":{"score":151,"line":["d4b2","g1e2"]},"c1e3":{"score":154,"line":["d4b4","e4d2"]},"c1f4":{"score":53,"line":["g8f6"]},"c1g5":{"score":155,"line":["d4b2","g1f3"]},"c1h6":{"score":605,"line":["g8h6"]},"a1b1":{"score":46,"line":["g8f6"]},"h2h3":{"score":85,"line":["g8f6","g1f3"]},"h2h4":{"score":58,"line":["g8f6","g1f3"]},"g2g3":{"score":47,"line":["d4b4","c2c3"]},"g2g4":{"score":105,"line":["g8f6","g1e2"]},"f2f3":{"score":134,"line":["d4b6","d1e2"]},"f2f4":{"score":108,"line":["d4b6"]},"c2c3":{"score":39,"line":["d4d8","g1f3"]},"c2c4":{"score":147,"line":["f8b4"]},"b2b3":{"score":774,"line":["d4a1","a2a4","f8b4","e4d2","b8d7","g1e2"]},"b2b4":{"score":818,"line":["d4a1"]},"a2a3":{"score":69,"line":["d4b6"]},"a2a4":{"score":28,"line":["g8f6"]},"d3e2":{"score":543,"line":["d4e4"]},"d3f1":{"score":616,"line":["d4e4"]},"d3c4":{"score":752,"line":["d4e4"]},"d3b5":{"score":752,"line":["d4e4"]},"d3a6":{"score":750,"line":["d4e4","a6e2"]},"e4c5":{"score":597,"line":["f8c5","d1e2"]},"e4g5":{"score":85,"line":["d4e5","g5e4"]},"e4c3":{"score":104,"line":["g8f6"]},"e4g3":{"score":109,"line":["d4e5","g3e4"]},"e4d6":{"score":580,"line":["d4d6","g1f3"]},"e4f6":{"score":590,"line":["g8f6","g1f3"]},"e4d2":{"score":103,"line":["d4e5","d2e4"]}},"bestMove":"b2b4"},"rn1qkbnr/pp2pppp/8/3pP3/3p2b1/N4N2/PPP2PPP/R1BQKB1R w KQkq - 2 6":{"moves":{"h1g1":{"score":161,"line":["b8c6","a3b5"]},"f1e2":{"score":145,"line":["g4f3"]},"f1d3":{"score":163,"line":["e7e6","e1g1"]},"f1c4":{"score":395,"line":["d5c4"]},"f1b5":{"score":131,"line":["b8c6","d1d4"]},"f1a6":{"score":648,"line":["b7a6"]},"e1e2":{"score":323,"line":["b8c6","h2h3"]},"e1d2":{"score":346,"line":["e7e6","f1b5"]},"d1d2":{"score":184,"line":["g4f3","g2f3"]},"d1d3":{"score":174,"line":["g4f3"]},"d1d4":{"score":116,"line":["g4f3","g2f3"]},"d1e2":{"score":206,"line":["b8c6","h2h3"]},"c1d2":{"score":199,"line":["b8c6"]},"c1e3":{"score":659,"line":["d4e3"]},"c1f4":{"score":133,"line":["a7a6"]},"c1g5":{"score":187,"line":["b8c6","f1b5"]},"c1h6":{"score":677,"line":["g8h6","a3b5"]},"a1b1":{"score":156,"line":["b8c6"]},"h2h3":{"score":175,"line":["g4f3","d1f3"]},"h2h4":{"score":171,"line":["a7a6"]},"g2g3":{"score":236,"line":["e7e6"]},"c2c3":{"score":108,"line":["d4c3"]},"c2c4":{"score":123,"line":["b8c6"]},"b2b3":{"score":267,"line":["a7a6","d1d4"]},"b2b4":{"score":248,"line":["e7e6"]},"f3d4":{"score":789,"line":["g4d1","f1b5","b8d7","e5e6","f7e6","d4e6"]},"f3h4":{"score":947,"line":["g4d1"]},"f3d2":{"score":926,"line":["g4d1","e1d1"]},"f3g5":{"score":924,"line":["g4d1","e1d1"]},"f3g1":{"score":937,"line":["g4d1","e1d1","d8b6","h2h3","b8c6","f2f4"]},"a3c4":{"score":388,"line":["d5c4","d1d4"]},"a3b5":{"score":28,"line":["e7e6"]},"a3b1":{"score":177,"line":["b8c6"]},"e5e6":{"score":130,"line":["f7e6"]}},"bestMove":"f3h4"},"r1bqkbnr/pp1npppp/2p5/8/3PN3/8/PPP2PPP/R1BQKBNR w KQkq - 1 5":{"moves":{"g1e2":{"score":22,"line":["g8f6"]},"g1f3":{"score":-16,"line":["g8f6"]},"g1h3":{"score":47,"line":["d7f6"]},"f1e2":{"score":0,"line":["g8f6","e4f6"]},"f1d3":{"score":-8,"line":["g8f6","e4f6"]},"f1c4":{"score":-11,"line":["g8f6","e4f6"]},"f1b5":{"score":512,"line":["c6b5"]},"f1a6":{"score":500,"line":["d8a5"]},"e1e2":{"score":143,"line":["g8f6","e4f6"]},"e1d2":{"score":118,"line":["g8f6"]},"d1d2":{"score":15,"line":["g8f6"]},"d1d3":{"score":-14,"line":["g8f6","g1f3"]},"d1e2":{"score":-31,"line":["d7f6"]},"d1f3":{"score":18,"line":["g8f6"]},"d1g4":{"score":150,"line":["d7c5"]},"d1h5":{"score":11,"line":["d7f6","h5e5"]},"c1d2":{"score":31,"line":["d7f6"]},"c1e3":{"score":0,"line":["g8f6","e4c3"]},"c1f4":{"score":3,"line":["g8f6"]},"c1g5":{"score":30,"line":["g8f6","e4f6"]},"c1h6":{"score":550,"line":["g8h6"]},"a1b1":{"score":3,"line":["g8f6","e4f6"]},"h2h3":{"score":-16,"line":["g8f6"]},"h2h4":{"score":37,"line":["d7f6"]},"g2g3":{"score":19,"line":["d7f6","e4c3"]},"g2g4":{"score":162,"line":["d7f6"]},"f2f3":{"score":64,"line":["g8f6","e4f6","d7f6","c2c3","e7e6","f3f4"]},"f2f4":{"score":73,"line":["g8f6"]},"c2c3":{"score":-23,"line":["g8f6"]},"c2c4":{"score":0,"line":["g8f6","e4c3"]},"b2b3":{"score":3,"line":["g8f6","e4f6"]},"b2b4":{"score":65,"line":["g8f6","e4f6"]},"a2a3":{"score":-7,"line":["g8f6","e4f6"]},"a2a4":{"score":-18,"line":["g8f6","e4f6"]},"e4c5":{"score":163,"line":["d7c5","d4c5"]},"e4g5":{"score":-19,"line":["g8f6"]},"e4c3":{"score":3,"line":["g8f6"]},"e4g3":{"score":10,"line":["g8f6"]},"e4d6":{"score":460,"line":["e7d6","g1f3"]},"e4f6":{"score":501,"line":["g8f6","g1f3"]},"e4d2":{"score":16,"line":["g8f6","g1f3"]},"d4d5":{"score":40,"line":["d8a5"]},"d4d6":{"score":121,"line":["g8f6"]}},"bestMove":"c1h6"},"rnbqkbnr/pp3ppp/4p3/3p4/2PP4/8/PP3PPP/RNBQKBNR w KQkq - 0 5":{"moves":{"g1e2":{"score":94,"line":["d5c4"]},"g1f3":{"score":3,"line":["g8f6"]},"g1h3":{"score":73,"line":["g8f6"]},"f1e2":{"score":8,"line":["g8f6","g1f3"]},"f1d3":{"score":10,"line":["d5c4","d3c4"]},"e1e2":{"score":237,"line":["d5c4","g1f3"]},"e1d2":{"score":217,"line":["d5c4","d2e1"]},"d1d2":{"score":69,"line":["g8f6"]},"d1d3":{"score":70,"line":["d5c4","d3c4"]},"d1c2":{"score":50,"line":["b8c6","g1f3"]},"d1b3":{"score":77,"line":["d5c4"]},"d1a4":{"score":61,"line":["b8c6"]},"d1e2":{"score":77,"line":["d5c4"]},"d1f3":{"score":119,"line":["b8c6"]},"d1g4":{"score":92,"line":["g8f6"]},"d1h5":{"score":128,"line":["b8c6","g1f3"]},"c1d2":{"score":46,"line":["d5c4"]},"c1e3":{"score":40,"line":["g8f6"]},"c1f4":{"score":25,"line":["g8f6"]},"c1g5":{"score":495,"line":["d8g5"]},"c1h6":{"score":529,"line":["g8h6","g1f3"]},"b1d2":{"score":58,"line":["b8c6","g1f3"]},"b1a3":{"score":91,"line":["f8a3"]},"b1c3":{"score":-11,"line":["g8f6"]},"h2h3":{"score":3,"line":["g8f6","g1f3"]},"h2h4":{"score":81,"line":["b8c6"]},"g2g3":{"score":54,"line":["d5c4","f1c4"]},"g2g4":{"score":127,"line":["b8c6"]},"f2f3":{"score":124,"line":["b8c6","c4d5"]},"f2f4":{"score":89,"line":["g7g6","b1c3"]},"b2b3":{"score":60,"line":["b8c6"]},"b2b4":{"score":179,"line":["f8b4","c1d2"]},"a2a3":{"score":26,"line":["b8c6"]},"a2a4":{"score":81,"line":["f8b4"]},"c4c5":{"score":31,"line":["e6e5","b1c3"]},"c4c6":{"score":152,"line":["b8c6","g1f3"]},"c4d5":{"score":30,"line":["e6d5"]}},"bestMove":"c1h6"},"rnbqkb1r/pp2pppp/2p2n2/8/3Pp3/8/PPPNNPPP/R1BQKB1R w KQkq - 2 5":{"moves":{"h1g1":{"score":183,"line":["g7g6","e2g3"]},"a1b1":{"score":173,"line":["c8f5","h2h3"]},"h2h3":{"score":81,"line":["c6c5","d4c5"]},"h2h4":{"score":126,"line":["c8f5","e2g3"]},"g2g3":{"score":119,"line":["c8f5"]},"g2g4":{"score":226,"line":["c8g4","f1g2"]},"f2f3":{"score":144,"line":["e4f3","d2f3"]},"f2f4":{"score":186,"line":["h7h5","e2g3"]},"e2c3":{"score":159,"line":["c8f5","f2f3"]},"e2g3":{"score":162,"line":["d8d4"]},"e2g1":{"score":264,"line":["d8d4","g1e2"]},"e2f4":{"score":248,"line":["d8d4"]},"d2b3":{"score":128,"line":["c8f5","h2h3"]},"d2f3":{"score":542,"line":["e4f3","g2f3"]},"d2b1":{"score":205,"line":["c8f5"]},"d2c4":{"score":154,"line":["c8f5"]},"d2e4":{"score":450,"line":["f6e4"]},"c2c3":{"score":81,"line":["c8f5","e2g3"]},"c2c4":{"score":146,"line":["c8f5","d1b3"]},"b2b3":{"score":150,"line":["g7g6","g2g3"]},"b2b4":{"score":193,"line":["e7e5"]},"a2a3":{"score":171,"line":["c8f5"]},"a2a4":{"score":108,"line":["c8f5"]},"d4d5":{"score":378,"line":["c6d5"]},"d4d6":{"score":356,"line":["e7d6"]}},"bestMove":"d2f3"},"rnbqkbnr/pp2pppp/2p5/8/3Pp3/2N5/PPP2PPP/R1BQKBNR w KQkq - 0 4":{"moves":{"g1e2":{"score":46,"line":["f7f5"]},"g1f3":{"score":554,"line":["e4f3"]},"g1h3":{"score":150,"line":["g8f6"]},"f1e2":{"score":131,"line":["g8f6","f2f3"]},"f1d3":{"score":479,"line":["e4d3","d1d3"]},"f1c4":{"score":110,"line":["g8f6","g1e2"]},"f1b5":{"score":496,"line":["c6b5"]},"f1a6":{"score":571,"line":["b8a6","c3e4"]},"e1e2":{"score":236,"line":["f7f5"]},"e1d2":{"score":302,"line":["d8d4"]},"d1d2":{"score":96,"line":["g8f6"]},"d1d3":{"score":1320,"line":["e4d3","f1d3"]},"d1e2":{"score":127,"line":["g8f6"]},"d1f3":{"score":1246,"line":["e4f3"]},"d1g4":{"score":1331,"line":["c8g4"]},"d1h5":{"score":124,"line":["g8f6","h5e5"]},"c1d2":{"score":143,"line":["g8f6"]},"c1e3":{"score":91,"line":["g8f6","f2f3"]},"c1f4":{"score":104,"line":["g8f6"]},"c1g5":{"score":113,"line":["h7h6"]},"c1h6":{"score":552,"line":["g8h6"]},"a1b1":{"score":146,"line":["g8f6","f2f3"]},"h2h3":{"score":116,"line":["f7f5","c1g5"]},"h2h4":{"score":132,"line":["g8f6","g1e2"]},"g2g3":{"score":128,"line":["g8f6","f1g2"]},"g2g4":{"score":105,"line":["e7e5","c1e3"]},"f2f3":{"score":82,"line":["e4f3","g1f3"]},"f2f4":{"score":224,"line":["f7f5","d4d5"]},"b2b3":{"score":148,"line":["g8f6","g1e2"]},"b2b4":{"score":166,"line":["g8f6"]},"a2a3":{"score":93,"line":["g8f6","h2h3"]},"a2a4":{"score":136,"line":["g8f6","f2f3"]},"c3a4":{"score":172,"line":["g8f6"]},"c3e4":{"score":-15,"line":["g8f6","e4f6"]},"c3e2":{"score":169,"line":["g8f6","f2f3"]},"c3b5":{"score":491,"line":["c6b5"]},"c3d5":{"score":672,"line":["c6d5","f1b5"]},"c3b1":{"score":183,"line":["g8f6"]},"d4d5":{"score":167,"line":["g8f6","d5c6"]},"d4d6":{"score":192,"line":["e7d6","c3e4"]}},"bestMove":"d1g4"},"rnbqk1nr/pp2ppbp/2p3p1/3pP3/3P4/8/PPPN1PPP/R1BQKBNR w KQkq - 1 5":{"moves":{"g1e2":{"score":33,"line":["f7f6"]},"g1f3":{"score":-34,"line":["g8h6","f1d3"]},"g1h3":{"score":92,"line":["c8h3","g2h3"]},"f1e2":{"score":-15,"line":["g8h6","g1f3"]},"f1d3":{"score":-32,"line":["c6c5"]},"f1c4":{"score":438,"line":["d5c4"]},"f1b5":{"score":472,"line":["c6b5","g1f3"]},"f1a6":{"score":508,"line":["b8a6"]},"e1e2":{"score":240,"line":["f7f6"]},"d1e2":{"score":50,"line":["g8h6","g1f3"]},"d1f3":{"score":38,"line":["c6c5"]},"d1g4":{"score":1271,"line":["c8g4","d2f3","g4c8","f1d3","e7e6","g1e2"]},"d1h5":{"score":1208,"line":["g6h5","g1e2"]},"a1b1":{"score":35,"line":["g8h6","d2b3"]},"h2h3":{"score":-30,"line":["f7f6","g1f3"]},"h2h4":{"score":53,"line":["c6c5","g1f3"]},"g2g3":{"score":30,"line":["c6c5"]},"g2g4":{"score":73,"line":["c6c5"]},"f2f3":{"score":57,"line":["c6c5","f1b5"]},"f2f4":{"score":-50,"line":["g8h6"]},"d2b3":{"score":-16,"line":["g8h6"]},"d2f3":{"score":3,"line":["c6c5","c2c3"]},"d2b1":{"score":77,"line":["f7f6","f2f4"]},"d2c4":{"score":388,"line":["d5c4","f1c4"]},"d2e4":{"score":484,"line":["d5e4"]},"c2c3":{"score":-31,"line":["g8h6"]},"c2c4":{"score":9,"line":["g8h6"]},"b2b3":{"score":47,"line":["c6c5","c2c3"]},"b2b4":{"score":3,"line":["f7f6","f2f4"]},"a2a3":{"score":-3,"line":["g8h6","d2b3"]},"a2a4":{"score":-9,"line":["g8h6","d2b3"]},"e5e6":{"score":163,"line":["c8e6"]}},"bestMove":"d1g4"},"r1bqkb1r/pp3ppp/n1p1pn2/3p4/3PP3/2N5/PPPQ1PPP/R1B1KBNR w KQkq - 0 6":{"moves":{"g1e2":{"score":150,"line":["f6e4"]},"g1f3":{"score":127,"line":["f6e4"]},"g1h3":{"score":85,"line":["f8b4","e4e5"]},"f1e2":{"score":116,"line":["f6e4"]},"f1d3":{"score":106,"line":["d5e4","d3e4"]},"f1c4":{"score":458,"line":["d5c4","g1f3"]},"f1b5":{"score":463,"line":["c6b5"]},"f1a6":{"score":45,"line":["b7a6","e4e5"]},"e1e2":{"score":264,"line":["d5e4","f2f3"]},"e1d1":{"score":280,"line":["d5e4","f2f3"]},"a1b1":{"score":107,"line":["d5e4","g1e2"]},"h2h3":{"score":106,"line":["f6e4","c3e4"]},"h2h4":{"score":127,"line":["d5e4"]},"g2g3":{"score":81,"line":["f6e4"]},"g2g4":{"score":158,"line":["f6e4"]},"f2f3":{"score":81,"line":["c6c5"]},"f2f4":{"score":164,"line":["d5e4"]},"d2d3":{"score":115,"line":["d5e4","c3e4"]},"d2d1":{"score":147,"line":["d5e4"]},"d2e2":{"score":160,"line":["d5e4"]},"d2e3":{"score":109,"line":["a6b4","f1d3"]},"d2f4":{"score":197,"line":["a6b4"]},"d2g5":{"score":189,"line":["a6b4"]},"d2h6":{"score":1221,"line":["g7h6"]},"b2b3":{"score":157,"line":["f8b4","c1b2"]},"b2b4":{"score":329,"line":["f8b4"]},"a2a3":{"score":70,"line":["f6e4","c3e4"]},"a2a4":{"score":123,"line":["d5e4"]},"c3a4":{"score":268,"line":["f6e4"]},"c3e2":{"score":238,"line":["f6e4","d2d1"]},"c3b5":{"score":549,"line":["f6e4"]},"c3d5":{"score":480,"line":["f6e4"]},"c3b1":{"score":225,"line":["f6e4","d2d1"]},"c3d1":{"score":267,"line":["f6e4","d2e3"]},"e4e5":{"score":7,"line":["f6d7"]},"e4d5":{"score":34,"line":["e6d5"]}},"bestMove":"d2h6"},"rn1qkbnr/pp3ppp/2p1p3/3pPb2/3P4/2P5/PP3PPP/RNBQKBNR w KQkq - 0 5":{"moves":{"g1e2":{"score":13,"line":["b8d7","e2g3","f5g6","f1d3","c6c5","d3g6"]},"g1f3":{"score":-7,"line":["b8d7","f1e2"]},"g1h3":{"score":77,"line":["f5h3"]},"f1e2":{"score":-22,"line":["g8e7","g1f3"]},"f1d3":{"score":21,"line":["g8e7","c1e3","f5d3","d1d3","e7f5","g1e2"]},"f1c4":{"score":505,"line":["d5c4","b1d2"]},"f1b5":{"score":499,"line":["c6b5"]},"f1a6":{"score":492,"line":["b8a6"]},"e1e2":{"score":180,"line":["c6c5"]},"e1d2":{"score":175,"line":["c6c5","g1f3"]},"d1d2":{"score":50,"line":["c6c5"]},"d1d3":{"score":813,"line":["f5d3"]},"d1c2":{"score":1274,"line":["f5c2","f1e2"]},"d1b3":{"score":26,"line":["d8c7"]},"d1a4":{"score":85,"line":["f7f6","g1f3"]},"d1e2":{"score":82,"line":["c6c5"]},"d1f3":{"score":62,"line":["g8e7","f1d3","c6c5","g1e2","b8c6","e1g1"]},"d1g4":{"score":1243,"line":["f5g4","f1e2"]},"d1h5":{"score":109,"line":["b8d7","h5e2"]},"c1d2":{"score":81,"line":["b8d7","g1f3"]},"c1e3":{"score":5,"line":["b8d7","b1d2","f7f6","g1f3","d8c7","e3f4"]},"c1f4":{"score":39,"line":["c6c5","f1d3"]},"c1g5":{"score":466,"line":["d8g5","h2h4","g5d8","g2g4","f5e4","f2f3"]},"c1h6":{"score":535,"line":["g8h6"]},"b1d2":{"score":-10,"line":["b8d7","d2b3"]},"b1a3":{"score":94,"line":["f8a3"]},"h2h3":{"score":42,"line":["g8e7"]},"h2h4":{"score":23,"line":["h7h6","c1e3"]},"g2g3":{"score":22,"line":["c6c5"]},"g2g4":{"score":88,"line":["f5g6"]},"f2f3":{"score":82,"line":["c6c5","f1b5"]},"f2f4":{"score":71,"line":["c6c5"]},"b2b3":{"score":45,"line":["g8e7","g1f3"]},"b2b4":{"score":46,"line":["g8e7"]},"a2a3":{"score":36,"line":["b8d7"]},"a2a4":{"score":7,"line":["g8e7"]},"c3c4":{"score":53,"line":["f8b4"]},"c3c5":{"score":57,"line":["b7b6"]}},"bestMove":"d1c2"},"rnb1kb1r/pp3ppp/1qp1pn2/3p4/3PP3/2NBB3/PPP2PPP/R2QK1NR w KQkq - 4 6":{"moves":{"g1e2":{"score":84,"line":["d5e4"]},"g1f3":{"score":18,"line":["b6b2"]},"g1h3":{"score":96,"line":["b6b2"]},"e1e2":{"score":237,"line":["b6b2","e4e5"]},"e1f1":{"score":112,"line":["b6b2"]},"e1d2":{"score":157,"line":["b6b2"]},"d1d2":{"score":106,"line":["d5e4","c3e4"]},"d1c1":{"score":0,"line":["d5e4","c3e4"]},"d1b1":{"score":35,"line":["c6c5","g1f3"]},"d1e2":{"score":648,"line":["b6b2"]},"d1f3":{"score":723,"line":["b6b2"]},"d1g4":{"score":1267,"line":["f6g4","e1c1"]},"d1h5":{"score":1265,"line":["f6h5"]},"a1b1":{"score":-15,"line":["c6c5","e4d5"]},"a1c1":{"score":93,"line":["b6b2","g1e2"]},"h2h3":{"score":80,"line":["b6b2"]},"h2h4":{"score":119,"line":["b6b2"]},"g2g3":{"score":80,"line":["b6b2"]},"g2g4":{"score":179,"line":["f6g4","e3d2"]},"f2f3":{"score":71,"line":["d5e4","f3e4"]},"f2f4":{"score":144,"line":["b6b2","g1e2"]},"b2b3":{"score":253,"line":["f8b4","e3d2"]},"b2b4":{"score":413,"line":["f8b4"]},"a2a3":{"score":18,"line":["f6e4","c3e4"]},"a2a4":{"score":61,"line":["b6b2"]},"e3d2":{"score":216,"line":["d5e4","c3e4"]},"e3c1":{"score":131,"line":["b6d4"]},"e3f4":{"score":84,"line":["c6c5"]},"e3g5":{"score":114,"line":["b6d4"]},"e3h6":{"score":436,"line":["g7h6"]},"d3e2":{"score":178,"line":["b6b2"]},"d3f1":{"score":223,"line":["b6b2","e3d2"]},"d3c4":{"score":481,"line":["b6b2"]},"d3b5":{"score":460,"line":["c6b5","e4e5","f6d7","a2a3","b8c6","g1e2"]},"d3a6":{"score":609,"line":["b8a6","e4e5"]},"c3a4":{"score":122,"line":["b6a5","c2c3"]},"c3e2":{"score":509,"line":["d5e4","d3e4"]},"c3b5":{"score":564,"line":["d5e4"]},"c3d5":{"score":327,"line":["e6d5","e4e5"]},"c3b1":{"score":256,"line":["d5e4","d3c4"]},"e4e5":{"score":19,"line":["f6d7","a2a3"]},"e4d5":{"score":26,"line":["e6d5"]}},"bestMove":"d1g4"},"rn1qkbnr/1p2pppp/2p5/3pPb2/p2P4/5N1P/PPP2PP1/RNBQKB1R w KQkq - 0 6":{"moves":{"h1h2":{"score":88,"line":["e7e6"]},"h1g1":{"score":76,"line":["e7e6"]},"f1e2":{"score":-9,"line":["e7e6","e1g1"]},"f1d3":{"score":7,"line":["f5d3"]},"f1c4":{"score":473,"line":["d5c4"]},"f1b5":{"score":453,"line":["c6b5"]},"f1a6":{"score":506,"line":["a8a6","f3h4"]},"e1e2":{"score":109,"line":["e7e6","e2e1"]},"e1d2":{"score":121,"line":["c6c5"]},"d1d2":{"score":9,"line":["e7e6"]},"d1d3":{"score":780,"line":["f5d3","f1d3"]},"d1e2":{"score":26,"line":["e7e6","a2a3"]},"c1d2":{"score":9,"line":["e7e6"]},"c1e3":{"score":-15,"line":["e7e6","f1d3"]},"c1f4":{"score":15,"line":["e7e6"]},"c1g5":{"score":22,"line":["h7h6"]},"c1h6":{"score":513,"line":["g8h6","g2g4"]},"b1d2":{"score":3,"line":["e7e6","f1e2"]},"b1a3":{"score":34,"line":["e7e6"]},"b1c3":{"score":9,"line":["e7e6"]},"g2g3":{"score":30,"line":["e7e6"]},"g2g4":{"score":-24,"line":["f5e4","e5e6","f7e6","b1d2","g8f6","f1g2"]},"c2c3":{"score":11,"line":["e7e6"]},"c2c4":{"score":-27,"line":["d5c4"]},"b2b3":{"score":39,"line":["a4b3","c2b3"]},"b2b4":{"score":34,"line":["a4b3"]},"a2a3":{"score":-4,"line":["e7e6"]},"h3h4":{"score":57,"line":["e7e6"]},"h3h5":{"score":0,"line":["e7e6","f3h4","f5e4","b1c3","b8d7","h4f3"]},"f3h4":{"score":-3,"line":["f5e4"]},"f3d2":{"score":26,"line":["e7e6"]},"f3h2":{"score":25,"line":["e7e6","h2f3","g8e7","b1c3","b8d7","f1e2"]},"f3g5":{"score":44,"line":["e7e6","g5f3","g8e7","b1c3","f5g6","f1d3"]},"f3g1":{"score":21,"line":["e7e6"]},"e5e6":{"score":87,"line":["f5e6","f1d3","g8f6","e1g1","g7g6","d1e2"]}},"bestMove":"d1d3"},"rnbqkbnr/pp2pp1p/2p3p1/8/2PP4/2N5/PP3PPP/R1BQKBNR w KQkq - 0 6":{"moves":{"g1e2":{"score":21,"line":["f8g7"]},"g1f3":{"score":-62,"line":["f8g7"]},"g1h3":{"score":77,"line":["f8g7"]},"f1e2":{"score":-3,"line":["f8g7","g1f3"]},"f1d3":{"score":85,"line":["d8d4","g1f3"]},"e1e2":{"score":131,"line":["f8g7"]},"e1d2":{"score":253,"line":["d8d4"]},"d1d2":{"score":38,"line":["f8g7"]},"d1d3":{"score":4,"line":["f8g7","g1f3"]},"d1c2":{"score":69,"line":["d8d4","c1e3"]},"d1b3":{"score":106,"line":["d8d4"]},"d1a4":{"score":105,"line":["d8d4","g1f3"]},"d1e2":{"score":92,"line":["d8d4","c1e3"]},"d1f3":{"score":116,"line":["d8d4"]},"d1g4":{"score":1243,"line":["c8g4","h2h3"]},"d1h5":{"score":1235,"line":["g6h5","g1f3"]},"c1d2":{"score":66,"line":["d8d4","g1f3"]},"c1e3":{"score":15,"line":["g8h6"]},"c1f4":{"score":-27,"line":["f8g7"]},"c1g5":{"score":-38,"line":["f8g7","g1f3"]},"c1h6":{"score":585,"line":["g8h6"]},"a1b1":{"score":15,"line":["f8g7","g1f3"]},"h2h3":{"score":-65,"line":["f8g7","g1f3"]},"h2h4":{"score":-14,"line":["f8g7","g1f3"]},"g2g3":{"score":-18,"line":["g8h6","f1g2"]},"g2g4":{"score":46,"line":["f8g7"]},"f2f3":{"score":0,"line":["f8g7","c1e3","g8f6","f1d3","b8d7","g1e2"]},"f2f4":{"score":26,"line":["h7h5"]},"b2b3":{"score":61,"line":["g8h6"]},"b2b4":{"score":35,"line":["e7e5","d4e5"]},"a2a3":{"score":-10,"line":["f8g7"]},"a2a4":{"score":31,"line":["f8g7","g1f3"]},"c3a4":{"score":47,"line":["f8g7"]},"c3e4":{"score":33,"line":["f8g7"]},"c3e2":{"score":47,"line":["f8g7","g1f3"]},"c3b5":{"score":453,"line":["c6b5"]},"c3d5":{"score":541,"line":["c6d5"]},"c3b1":{"score":69,"line":["f8g7"]},"d4d5":{"score":34,"line":["g8f6"]},"d4d6":{"score":60,"line":["d8d6","d1d6","e7d6","c1f4","c8e6","e1c1"]},"c4c5":{"score":0,"line":["f8g7","g1f3","c8e6","f1e2","g8f6","e1g1"]}},"bestMove":"d1g4"},"rnbqkb1r/pp2pppp/2p2n2/3p4/3PP3/2N5/PPP2PPP/R1BQKBNR w KQkq - 2 4":{"moves":{"g1e2":{"score":42,"line":["f6e4"]},"g1f3":{"score":123,"line":["d5e4","f3e5"]},"g1h3":{"score":155,"line":["d5e4","c1e3"]},"f1e2":{"score":131,"line":["d5e4"]},"f1d3":{"score":30,"line":["d5e4"]},"f1c4":{"score":434,"line":["d5c4"]},"f1b5":{"score":413,"line":["c6b5","e4e5","b5b4","e5f6","b4c3","f6g7"]},"f1a6":{"score":481,"line":["b8a6"]},"e1e2":{"score":259,"line":["f6e4"]},"e1d2":{"score":256,"line":["d5e4"]},"d1d2":{"score":140,"line":["d5e4","f2f3"]},"d1d3":{"score":11,"line":["b8a6"]},"d1e2":{"score":118,"line":["d5e4"]},"d1f3":{"score":140,"line":["d5e4","c3e4"]},"d1g4":{"score":1250,"line":["c8g4","e4d5"]},"d1h5":{"score":1273,"line":["f6h5"]},"c1d2":{"score":143,"line":["d5e4","g1e2"]},"c1e3":{"score":97,"line":["d5e4","f2f3"]},"c1f4":{"score":116,"line":["d5e4","f2f3"]},"c1g5":{"score":116,"line":["f6e4","c3e4"]},"c1h6":{"score":399,"line":["g7h6"]},"a1b1":{"score":154,"line":["f6e4"]},"h2h3":{"score":112,"line":["f6e4"]},"h2h4":{"score":129,"line":["d5e4","g1e2"]},"g2g3":{"score":131,"line":["d5e4"]},"g2g4":{"score":179,"line":["c8g4","f1e2"]},"f2f3":{"score":34,"line":["d5e4","f3e4"]},"f2f4":{"score":193,"line":["d5e4"]},"b2b3":{"score":166,"line":["d5e4","f2f3"]},"b2b4":{"score":174,"line":["f6e4"]},"a2a3":{"score":116,"line":["f6e4"]},"a2a4":{"score":128,"line":["d5e4","f2f3"]},"c3a4":{"score":182,"line":["d5e4"]},"c3e2":{"score":128,"line":["d5e4","f2f3"]},"c3b5":{"score":360,"line":["c6b5","e4e5"]},"c3d5":{"score":249,"line":["c6d5"]},"c3b1":{"score":171,"line":["d5e4","b1c3"]},"e4e5":{"score":-8,"line":["f6d7","c3e2"]},"e4e6":{"score":176,"line":["c8e6","f1d3","e6g4","g1e2","b8d7","f2f3"]},"e4d5":{"score":39,"line":["c6d5","c1f4"]}},"bestMove":"d1h5"},"rnbqkb1r/pp2pp1p/2p2np1/8/P2Pp3/2P5/1P1N1PPP/R1BQKBNR w KQkq - 1 6":{"moves":{"g1e2":{"score":113,"line":["c6c5","d4c5"]},"g1f3":{"score":447,"line":["e4f3","d2f3"]},"g1h3":{"score":124,"line":["c8f5","f1c4"]},"f1e2":{"score":127,"line":["f8g7"]},"f1d3":{"score":595,"line":["e4d3","g1f3"]},"f1c4":{"score":112,"line":["f8g7"]},"f1b5":{"score":525,"line":["c6b5","d1e2"]},"f1a6":{"score":651,"line":["b8a6"]},"e1e2":{"score":365,"line":["f8g7","e2e1"]},"d1c2":{"score":152,"line":["c8f5","c2b3"]},"d1b3":{"score":171,"line":["f8g7","f2f3"]},"d1e2":{"score":146,"line":["c8f5","f2f3"]},"d1f3":{"score":1212,"line":["e4f3","g1f3"]},"d1g4":{"score":1274,"line":["c8g4","g1e2"]},"d1h5":{"score":1267,"line":["g6h5"]},"a1a2":{"score":178,"line":["f8g7"]},"a1a3":{"score":185,"line":["b8d7"]},"a1b1":{"score":198,"line":["f8g7","g1e2"]},"h2h3":{"score":121,"line":["f8g7","d1c2"]},"h2h4":{"score":163,"line":["c6c5"]},"g2g3":{"score":123,"line":["c8f5"]},"g2g4":{"score":236,"line":["c8g4"]},"f2f3":{"score":120,"line":["e4f3","g1f3"]},"f2f4":{"score":220,"line":["c8f5","g1e2","h7h5","e2g3","h5h4","g3f5"]},"d2b3":{"score":159,"line":["f8g7","f2f3"]},"d2f3":{"score":470,"line":["e4f3"]},"d2b1":{"score":202,"line":["f8g7","f1c4"]},"d2c4":{"score":173,"line":["f8g7","f2f3"]},"d2e4":{"score":418,"line":["f6e4"]},"b2b3":{"score":206,"line":["f8g7","f1c4"]},"b2b4":{"score":172,"line":["a7a5"]},"c3c4":{"score":316,"line":["d8d4","f2f3"]},"c3c5":{"score":361,"line":["d8d4"]},"d4d5":{"score":415,"line":["c6d5","f2f3"]},"d4d6":{"score":334,"line":["e7d6"]},"a4a5":{"score":115,"line":["f8g7","g1e2"]},"a4a6":{"score":100,"line":["b7b5"]}},"bestMove":"d1g4"},"rnbqkbnr/pp2ppp1/2p4p/8/3Pp3/2N5/PPP1NPPP/R1BQKB1R w KQkq - 0 5":{"moves":{"h1g1":{"score":84,"line":["b8d7"]},"e1d2":{"score":249,"line":["g8f6","d2e1"]},"d1d2":{"score":22,"line":["g8f6","e2g3"]},"d1d3":{"score":1312,"line":["e4d3","c2d3","e7e6","c1e3","g8e7","e1c1"]},"c1d2":{"score":81,"line":["g8f6"]},"c1e3":{"score":-19,"line":["g8f6"]},"c1f4":{"score":41,"line":["g8f6","e2g3"]},"c1g5":{"score":544,"line":["h6g5","c3e4"]},"c1h6":{"score":450,"line":["h8h6"]},"a1b1":{"score":33,"line":["g8f6","e2g3"]},"h2h3":{"score":-4,"line":["g8f6"]},"h2h4":{"score":15,"line":["g8f6","e2g3"]},"g2g3":{"score":76,"line":["g8f6"]},"g2g4":{"score":202,"line":["c8g4","h1g1"]},"f2f3":{"score":154,"line":["e4f3"]},"f2f4":{"score":197,"line":["f7f5"]},"e2g3":{"score":-14,"line":["g8f6","c3e4"]},"e2g1":{"score":147,"line":["g8f6"]},"e2f4":{"score":119,"line":["g8f6"]},"b2b3":{"score":22,"line":["g8f6"]},"b2b4":{"score":72,"line":["a7a5"]},"a2a3":{"score":-5,"line":["g8f6","e2g3"]},"a2a4":{"score":26,"line":["g8f6","e2g3"]},"c3a4":{"score":161,"line":["c8f5","e2g3"]},"c3e4":{"score":3,"line":["g8f6"]},"c3b5":{"score":519,"line":["c6b5"]},"c3d5":{"score":626,"line":["c6d5"]},"c3b1":{"score":159,"line":["c8f5","c2c4"]},"d4d5":{"score":144,"line":["g8f6","d5c6"]},"d4d6":{"score":189,"line":["e7d6"]}},"bestMove":"d1d3"},"rnbqkbnr/pp2ppp1/2p4p/8/3Pp3/2N1B3/PPP2PPP/R2QKBNR w KQkq - 0 5":{"moves":{"g1e2":{"score":-19,"line":["g8f6"]},"g1f3":{"score":452,"line":["e4f3"]},"g1h3":{"score":112,"line":["g8f6"]},"f1e2":{"score":113,"line":["c8f5","f2f3"]},"f1d3":{"score":562,"line":["e4d3"]},"f1c4":{"score":101,"line":["b7b5","c4b3"]},"f1b5":{"score":514,"line":["c6b5"]},"f1a6":{"score":527,"line":["b8a6","c3e4"]},"e1e2":{"score":178,"line":["f7f5"]},"e1d2":{"score":210,"line":["g8f6","f2f3"]},"d1d2":{"score":65,"line":["g8f6"]},"d1d3":{"score":1240,"line":["e4d3","f1d3","e7e6","c3e4","g8e7","g1f3"]},"d1c1":{"score":139,"line":["c8f5","f2f3"]},"d1b1":{"score":133,"line":["g8f6"]},"d1e2":{"score":104,"line":["g8f6","e1c1"]},"d1f3":{"score":1238,"line":["e4f3"]},"d1g4":{"score":1218,"line":["c8g4","c3e4"]},"d1h5":{"score":141,"line":["g8f6"]},"a1b1":{"score":101,"line":["g8f6","f2f3"]},"a1c1":{"score":118,"line":["g8f6","f2f3"]},"h2h3":{"score":96,"line":["g8f6"]},"h2h4":{"score":153,"line":["g8f6"]},"g2g3":{"score":126,"line":["g8f6"]},"g2g4":{"score":85,"line":["g8f6","h2h3"]},"f2f3":{"score":58,"line":["e4f3"]},"f2f4":{"score":199,"line":["g8f6"]},"b2b3":{"score":148,"line":["g8f6","g1e2"]},"b2b4":{"score":174,"line":["g8f6"]},"a2a3":{"score":89,"line":["g8f6","f2f3"]},"a2a4":{"score":131,"line":["c8f5","f2f3"]},"e3d2":{"score":135,"line":["g8f6"]},"e3c1":{"score":147,"line":["g8f6"]},"e3f4":{"score":91,"line":["g8f6","f2f3"]},"e3g5":{"score":572,"line":["h6g5","c3e4"]},"e3h6":{"score":508,"line":["h8h6"]},"c3a4":{"score":172,"line":["c8f5"]},"c3e4":{"score":-30,"line":["c8f5","f1d3"]},"c3e2":{"score":156,"line":["c8f5"]},"c3b5":{"score":488,"line":["c6b5"]},"c3d5":{"score":684,"line":["c6d5"]},"c3b1":{"score":179,"line":["c8f5","g1e2"]},"d4d5":{"score":101,"line":["c8f5","f1c4"]},"d4d6":{"score":185,"line":["e7d6"]}},"bestMove":"d1d3"},"rnbqkb1r/pp2pppp/2p2n2/8/3PN3/8/PPP2PPP/R1BQKBNR w KQkq - 1 5":{"moves":{"g1e2":{"score":477,"line":["f6e4"]},"g1f3":{"score":440,"line":["f6e4"]},"g1h3":{"score":517,"line":["f6e4"]},"f1e2":{"score":452,"line":["f6e4","g1f3"]},"f1d3":{"score":78,"line":["d8d4","g1f3"]},"f1c4":{"score":450,"line":["f6e4"]},"f1b5":{"score":493,"line":["d8a5","c2c3"]},"f1a6":{"score":506,"line":["b8a6"]},"e1e2":{"score":531,"line":["f6e4"]},"e1d2":{"score":695,"line":["d8d4","d2e1"]},"d1d2":{"score":483,"line":["f6e4"]},"d1d3":{"score":-14,"line":["b8d7","g1f3"]},"d1e2":{"score":149,"line":["d8d4"]},"d1f3":{"score":112,"line":["d8d4"]},"d1g4":{"score":1207,"line":["f6g4"]},"d1h5":{"score":1230,"line":["f6h5"]},"c1d2":{"score":464,"line":["f6e4","d2e3"]},"c1e3":{"score":421,"line":["f6e4"]},"c1f4":{"score":465,"line":["f6e4"]},"c1g5":{"score":481,"line":["f6e4"]},"c1h6":{"score":439,"line":["f6e4","h6e3"]},"a1b1":{"score":469,"line":["f6e4"]},"h2h3":{"score":450,"line":["f6e4"]},"h2h4":{"score":450,"line":["f6e4","c2c3"]},"g2g3":{"score":431,"line":["f6e4","f1g2"]},"g2g4":{"score":508,"line":["f6e4"]},"f2f3":{"score":53,"line":["b8d7"]},"f2f4":{"score":518,"line":["f6e4","g1f3","g7g6","f1d3","e4d6","e1g1"]},"c2c3":{"score":429,"line":["f6e4"]},"c2c4":{"score":454,"line":["f6e4","a2a3"]},"b2b3":{"score":514,"line":["f6e4","g1f3"]},"b2b4":{"score":507,"line":["f6e4","c1b2"]},"a2a3":{"score":438,"line":["f6e4"]},"a2a4":{"score":437,"line":["f6e4","g1f3"]},"e4c5":{"score":38,"line":["e7e5","d4e5"]},"e4g5":{"score":60,"line":["e7e6"]},"e4c3":{"score":12,"line":["c8f5","f1d3"]},"e4g3":{"score":46,"line":["c6c5","c1e3"]},"e4d6":{"score":493,"line":["e7d6","f1d3"]},"e4f6":{"score":-34,"line":["e7f6"]},"e4d2":{"score":119,"line":["d8d4"]},"d4d5":{"score":627,"line":["f6e4"]},"d4d6":{"score":591,"line":["f6e4","c2c3"]}},"bestMove":"d1h5"},"rnbqkb1r/pp3ppp/4pn2/2p5/3Pp3/2P5/PPQNNPPP/R1B1KB1R w KQkq - 0 7":{"moves":{"h1g1":{"score":185,"line":["b8c6"]},"e1d1":{"score":318,"line":["c5d4","c3d4"]},"a1b1":{"score":139,"line":["b8c6"]},"h2h3":{"score":118,"line":["b8c6"]},"h2h4":{"score":167,"line":["c5d4","e2d4"]},"g2g3":{"score":104,"line":["c5d4"]},"g2g4":{"score":125,"line":["c5d4"]},"f2f3":{"score":186,"line":["e4f3","d2f3"]},"f2f4":{"score":210,"line":["e4f3"]},"e2g3":{"score":116,"line":["c5d4","d2e4"]},"e2g1":{"score":197,"line":["c5d4"]},"e2f4":{"score":140,"line":["c5d4","d2e4"]},"d2b3":{"score":93,"line":["c5d4","b3d4"]},"d2f3":{"score":585,"line":["e4f3"]},"d2b1":{"score":179,"line":["b8c6","c1e3"]},"d2c4":{"score":204,"line":["b7b5"]},"d2e4":{"score":34,"line":["f6e4","c2e4"]},"c2d1":{"score":184,"line":["c8d7"]},"c2b1":{"score":165,"line":["b8c6","d2e4"]},"c2b3":{"score":183,"line":["b8c6"]},"c2a4":{"score":195,"line":["c8d7"]},"c2d3":{"score":1383,"line":["e4d3","e2f4"]},"c2e4":{"score":816,"line":["f6e4"]},"b2b3":{"score":142,"line":["b8c6","d2e4"]},"b2b4":{"score":210,"line":["c5b4","d2e4"]},"a2a3":{"score":131,"line":["c5d4"]},"a2a4":{"score":108,"line":["b8c6"]},"c3c4":{"score":399,"line":["c5d4"]},"d4d5":{"score":450,"line":["e6d5","f2f3"]},"d4d6":{"score":240,"line":["e4e3"]},"d4c5":{"score":136,"line":["e4e3","f2e3"]}},"bestMove":"c2d3"},"rnbqkb1r/pp2pppp/2p2n2/3P4/3P4/8/PPP2PPP/RNBQKBNR w KQkq - 1 4":{"moves":{"g1e2":{"score":38,"line":["c6d5"]},"g1f3":{"score":0,"line":["c6d5","c2c3","c8f5","f3e5","b8c6","f1d3"]},"g1h3":{"score":89,"line":["c8g4","d1d3"]},"f1e2":{"score":4,"line":["c6d5","g1f3"]},"f1d3":{"score":0,"line":["c6d5","g1f3","c8g4","h2h3","g4h5","c2c3"]},"f1c4":{"score":36,"line":["c6d5"]},"f1b5":{"score":497,"line":["c6b5","g1e2"]},"f1a6":{"score":439,"line":["d8a5","c2c3"]},"e1e2":{"score":140,"line":["c6d5","e2e1"]},"e1d2":{"score":157,"line":["c6d5","d2e1"]},"d1d2":{"score":44,"line":["c6d5"]},"d1d3":{"score":49,"line":["c6d5","g1f3"]},"d1e2":{"score":39,"line":["c6d5","c2c3"]},"d1f3":{"score":61,"line":["c6d5"]},"d1g4":{"score":1211,"line":["c8g4"]},"d1h5":{"score":1165,"line":["f6h5","d5c6"]},"c1d2":{"score":56,"line":["c6d5"]},"c1e3":{"score":23,"line":["c6d5","f1d3"]},"c1f4":{"score":19,"line":["f6d5","f4c1"]},"c1g5":{"score":32,"line":["c6d5","g1f3"]},"c1h6":{"score":480,"line":["g7h6"]},"b1d2":{"score":0,"line":["c6d5","g1f3"]},"b1a3":{"score":49,"line":["c6d5"]},"b1c3":{"score":31,"line":["c6d5","c1f4"]},"h2h3":{"score":9,"line":["c6d5"]},"h2h4":{"score":42,"line":["c6d5"]},"g2g3":{"score":64,"line":["c6d5","g1f3","b8c6","c2c3","c8f5","c1f4"]},"g2g4":{"score":194,"line":["c8g4","f1e2"]},"f2f3":{"score":92,"line":["c6d5"]},"f2f4":{"score":74,"line":["c6d5","g1f3"]},"c2c3":{"score":7,"line":["c6d5"]},"c2c4":{"score":3,"line":["c6d5"]},"b2b3":{"score":73,"line":["c6d5"]},"b2b4":{"score":92,"line":["c6d5"]},"a2a3":{"score":30,"line":["c6d5"]},"a2a4":{"score":37,"line":["c6d5"]},"d5d6":{"score":27,"line":["e7d6","g1f3"]},"d5d7":{"score":22,"line":["b8d7"]},"d5c6":{"score":-74,"line":["b8c6"]}},"bestMove":"d1g4"},"r2qkbnr/pp1npppp/2p5/3pPb2/3P4/2P5/PP3PPP/RNBQKBNR w KQkq - 1 5":{"moves":{"g1e2":{"score":11,"line":["e7e6"]},"g1f3":{"score":-26,"line":["e7e6","f1e2"]},"g1h3":{"score":16,"line":["f5h3","g2h3"]},"f1e2":{"score":-22,"line":["e7e6","g1f3"]},"f1d3":{"score":7,"line":["f5d3"]},"f1c4":{"score":412,"line":["d5c4","b1d2"]},"f1b5":{"score":491,"line":["c6b5"]},"f1a6":{"score":461,"line":["b7a6","g1e2"]},"e1e2":{"score":183,"line":["e7e6"]},"e1d2":{"score":139,"line":["e7e6","g1f3"]},"d1d2":{"score":54,"line":["e7e6","f1d3"]},"d1d3":{"score":801,"line":["f5d3","f1d3"]},"d1c2":{"score":1266,"line":["f5c2","g1h3"]},"d1b3":{"score":16,"line":["a8b8","f1e2"]},"d1a4":{"score":73,"line":["e7e6","a4b3"]},"d1e2":{"score":61,"line":["e7e6"]},"d1f3":{"score":27,"line":["e7e6","f1d3"]},"d1g4":{"score":1246,"line":["f5g4","f1d3"]},"d1h5":{"score":103,"line":["e7e6","h5e2"]},"c1d2":{"score":43,"line":["e7e6","g1f3"]},"c1e3":{"score":-4,"line":["d8b6"]},"c1f4":{"score":19,"line":["e7e6","f1d3"]},"c1g5":{"score":82,"line":["f7f6","e5f6"]},"c1h6":{"score":549,"line":["g8h6"]},"b1d2":{"score":-3,"line":["e7e6","g1f3"]},"b1a3":{"score":-9,"line":["e7e6","a3c2"]},"h2h3":{"score":22,"line":["f7f6","f2f4"]},"h2h4":{"score":-7,"line":["h7h6","g2g4"]},"g2g3":{"score":0,"line":["e7e6","g1f3","g8e7","f1g2","e7g6","h2h4"]},"g2g4":{"score":67,"line":["f5e4"]},"f2f3":{"score":53,"line":["e7e6"]},"f2f4":{"score":-11,"line":["e7e6","g1f3"]},"b2b3":{"score":11,"line":["e7e6"]},"b2b4":{"score":31,"line":["e7e6","f1d3"]},"a2a3":{"score":22,"line":["e7e6"]},"a2a4":{"score":0,"line":["e7e6","f1d3"]},"c3c4":{"score":33,"line":["e7e6"]},"c3c5":{"score":38,"line":["e7e6"]},"e5e6":{"score":159,"line":["f5e6","f1d3"]}},"bestMove":"d1c2"}}